Workbook

Sheet KPI_Summary
A1: Jewellery Retail Analytics — KPI Dashboard
A2: All figures recalculate live from Cleaned_Sales / Cleaned_Products / Cleaned_Customers
A4: TOTAL REVENUE (₹) | C4: TOTAL ORDERS | E4: AVERAGE ORDER VALUE (₹) | G4: TOTAL ACTIVE CUSTOMERS
A5: =SUM(Cleaned_Sales!K2:K714) -> 139793971 | C5: =COUNTA(Cleaned_Sales!A2:A714) -> 713 | E5: =A5/C5 -> 196064.48 | G5: =SUMPRODUCT((COUNTIF(Cleaned_Sales!E2:E714,Cleaned_Sales!E2:E714))^-1) -> 149
A9: REPEAT CUSTOMER RATE | C9: AVERAGE DISCOUNT GIVEN | E9: TOTAL INVENTORY VALUE (₹) | G9: AVG PRODUCT MARGIN %
A10: =COUNTIF(Classification!D69:D217,">1")/COUNTIF(Classification!D69:D217,">=1") -> 0.98648649 | C10: =AVERAGE(Cleaned_Sales!J2:J714)/100 -> 0.051542777 | E10: =SUMPRODUCT(Cleaned_Products!G2:G61,Cleaned_Products!K2:K61) -> 420436440 | G10: =AVERAGE(Cleaned_Products!J2:J61)/100 -> 0.24706333
A14: TOP CATEGORY (by revenue) | C14: REVENUE — 2024 | E14: REVENUE — 2023 | G14: YoY GROWTH (2023→2024)
A15: =INDEX(Pivot_Tables!A5:A12,MATCH(MAX(Pivot_Tables!B5:B12),Pivot_Tables!B5:B12,0)) -> Bracelets | C15: =SUMIF(Cleaned_Sales!D2:D714,2024,Cleaned_Sales!K2:K714) -> 53965112 | E15: =SUMIF(Cleaned_Sales!D2:D714,2023,Cleaned_Sales!K2:K714) -> 56789550 | G15: =IFERROR((C15-E15)/E15,"N/A") -> -0.049735171
A19: ONLINE SALES SHARE | C19: PRODUCTS IN CLASS 'A' | E19: CHAMPION CUSTOMERS | G19: TOTAL SKUs ACTIVE
A20: =SUMIF(Cleaned_Sales!M2:M714,"Online",Cleaned_Sales!K2:K714)/A5 -> 0.51612117 | C20: =COUNTIF(Classification!H5:H64,"A - Top Contributor") -> 40 | E20: =COUNTIF(Classification!H69:H217,"Champion") -> 38 | G20: =COUNTIF(Cleaned_Products!K2:K61,">0") -> 58
A24: Notes on methodology
A25: • Revenue = Quantity × Unit Price × (1 − Discount%), computed on cleaned, deduplicated transactions only.
A26: • Repeat Customer Rate = customers with 2+ orders ÷ customers with 1+ orders (see Classification sheet).
A27: • ABC classification follows Pareto principle: Class A = top 80% cumulative revenue, B = next 15%, C = remaining 5%.
A28: • Customer segments (Champion/Loyal/At Risk/Occasional) use spend quartiles and 180-day recency threshold — see Classification sheet.
A29: • 2025 is a partial year in the source data (through Jul-2025) and is excluded from the YoY comparison above.

Sheet README
A1: Jewellery Retail Analytics — Raw Data Workbook
A3: This workbook contains intentionally messy, realistic raw data simulating exports from a POS/CRM system.
A4: Sheets:
A5: - Raw_Sales: 950+ transaction records (2023-2025) with duplicates, blanks, inconsistent formats
A6: - Raw_Products: 60+ SKUs across categories/materials with negative stock errors & mixed price formats
A7: - Raw_Customers: 150+ customers with inconsistent gender/city/date formats
A8: - Raw_Stores: 8 retail store locations
A10: Known data quality issues (deliberately injected for the cleaning exercise):
A11: 1. Mixed date formats (YYYY-MM-DD, DD/MM/YYYY, MM/DD/YYYY, DD-Mon-YYYY, Month DD YYYY, DD.MM.YYYY)
A12: 2. Inconsistent text casing (gold/Gold/GOLD, online/Online/ONLINE)
A13: 3. City name typos & variants (Bombay/Mumbai, Bangalore/Bengaluru)
A14: 4. Currency symbols & thousands separators mixed with plain numbers (₹45,000 / Rs. 45000 / 45000)
... A19: 9. Discount field mixing numbers, percent-strings, blanks and negative values

Sheet Raw_Sales
A1: TransactionID | B1: OrderDate | C1: CustomerID | D1: ProductID | E1: StoreID | F1: Quantity | G1: UnitPrice | H1: DiscountPct | I1: PaymentMode | J1: SalesChannel | K1: SalesRep
A2: TXN5488 | B2: 02/05/2023 | C2: C2102 | D2: P1032 | E2: S105 | F2: 1 | G2: 164590 | H2: 0 | I2: COD | J2: instore | K2: Indali Kala
A3: TXN5125 | B3: 27-Nov-2024 | C3: C2053 | D3: P1027 | E3: S108 | F3: 1 | G3: 95070 | H3: 15 | I3: UPI | J3: IN-STORE | K3: Wriddhish Kulkarni
A4: TXN5484 | B4: 25-Nov-2024 | C4: C2090 | D4: P1049 | E4: S107 | F4: -1 | G4: 21670 | H4: 15 | I4: EMI | J4: in-store | K4: Ucchal Mann
A5: TXN5198 | B5: 28.11.2023 | C5: C2042 | D5: P1046 | E5: S102 | F5: 1 | G5: 32080 | H5: 10% | I5: CC | J5: online | K5: Harinakshi Sidhu
A6: TXN5571 | B6: 20-Jul-2023 | C6: C2032 | D6: P1023 | E6: S108 | F6: -1 | G6: 227370 | I6: Credit_Card | J6: Web
A7: TXN5496 | B7: 27/10/2024 | C7: C2103 | D7: P1030 | E7: S102 | F7: 2 | G7: 170430 | H7: 5 | I7: Net Banking | J7: Web | K7: Anjali Korpal
A8: TXN5395 | B8: 27.03.2023 | C8: C2130 | D8: P1014 | E8: S103 | F8: 3 | G8: Rs. 136,950 | H8: 10 | I8: Net Banking | J8: in-store | K8: Finn Chanda
A9: TXN5719 | B9: 27.11.2023 | C9: C2027 | D9: P1041 | E9: S106 | F9: 1 | G9: 43050 | H9: 10% | I9: EMI | J9: Web
A10: TXN5273 | B10: 11.06.2024 | C10: C2094 | D10: P1057 | E10: S101 | F10: 1 | G10: 98210 | H10: 0 | I10: Upi | J10: online | K10: Yahvi Babu
A11: TXN5413 | B11: 10.05.2023 | C11: C2132 | D11: P1017 | E11: S106 | F11: -1 | G11: 122420 | H11: 5 | I11: Debit Card | J11: online
A12: TXN5469 | B12: 03/07/2023 | C12: C2008 | D12: P1038 | E12: S104 | F12: 0 | G12: 123360 | H12: 0 | I12: Credit_Card | J12: online
A13: TXN5222 | B13: 08-Mar-2023 | C13: C2029 | D13: P1023 | E13: S108 | F13: 0 | G13: 212,060.00 | H13: 10% | I13: Net Banking | J13: online | K13: Omaja Bose
A14: TXN5602 | B14: March 17, 2024 | C14: C2086 | D14: P1004 | E14: S108 | F14: 2 | G14: ₹94,970.00 | I14: EMI | J14: Web
A15: TXN5073 | B15: 04/12/2024 | C15: C2068 | D15: P1030 | E15: S101 | F15: 1 | G15: 204040 | H15: 15 | I15: UPI | J15: IN-STORE | K15: Prisha Kadakia
A16: TXN5842 | B16: 05/01/2023 | C16: C2085 | D16: P1012 | E16: S107 | F16: 2 | G16: 95460 | H16: 0 | I16: Debit Card | J16: Web | K16: Gavin Ghose
A17: TXN5280 | B17: 2023-10-23 | C17: C2038 | D17: P1023 | E17: S105 | F17: 0 | G17: 239230 | H17: 5 | I17: EMI | J17: ONLINE | K17: Harita Grover
A18: TXN5639 | B18: 07/25/2023 | C18: C2016 | D18: P1009 | E18: S104 | F18: 3 | G18: 231350 | H18: 0 | I18: Debit Card | J18: online
A19: TXN5190 | B19: 29.06.2024 | C19: C2031 | D19: P1012 | E19: S106 | F19: 1 | G19: 182860 | I19: CASH | J19: instore | K19: Irya Bath
A20: TXN5393 | B20: February 09, 2025 | C20: C2099 | D20: P1006 | E20: S102 | F20: 2 | G20: 18920 | I20: CC | J20: online | K20: Jalsa Sha
A21: TXN5126 | B21: 23/01/2025 | C21: C2031 | D21: P1048 | E21: S104 | F21: 0 | G21: 196640 | H21: 0 | I21: Debit Card | J21: in-store | K21: Dayamai Patil
A22: TXN5028 | B22: February 24, 2025 | C22: C2060 | D22: P1011 | E22: S102 | F22: 2 | G22: 165,590.00 | H22: 0 | I22: Debit Card | J22: In Store | K22: Hemal Zachariah
A23: TXN5604 | B23: 08/12/2024 | C23: C2062 | D23: P1005 | E23: S102 | F23: 2 | G23: 59710 | I23: CASH | J23: ONLINE | K23: Nicholas Cheema
A24: TXN5268 | B24: 15.01.2023 | C24: C2111 | D24: P1048 | E24: S104 | F24: 2 | G24: 84510 | H24: 5 | I24: Net Banking | J24: in-store | K24: Chakrika Batta
A25: TXN5675 | B25: 12/10/2023 | C25: C2118 | D25: P1041 | E25: S102 | F25: 3 | G25: ₹223,500.00 | H25: 0 | I25: EMI | J25: online | K25: Vivaan Lanka
A26: TXN5510 | B26: 11/03/2023 | C26: C2111 | D26: P1058 | E26: S103 | F26: 2 | G26: 30740 | H26: -5 | I26: Debit Card | J26: IN-STORE | K26: Krisha Parmar
A27: TXN5866 | B27: 27/07/2025 | C27: C2029 | D27: P1060 | E27: S104 | F27: 3 | G27: 75920 | H27: 0 | I27: UPI | J27: in-store | K27: Upasna Hayre
A28: TXN5112 | B28: August 02, 2024 | C28: C2038 | D28: P1048 | E28: S108 | F28: 3 | G28: 13940 | H28: 10 | I28: Credit_Card | J28: In Store | K28: Warinder Choudhury
A29: TXN5632 | B29: 29-Jan-2024 | C29: C2017 | D29: P1004 | E29: S105 | F29: 1 | G29: 13200 | H29: -5 | I29: UPI | J29: ONLINE
A30: TXN5205 | B30: 13/12/2024 | C30: C2015 | D30: P1007 | E30: S102 | F30: 0 | G30: 182120 | H30: 15 | I30: COD | J30: instore | K30: Qushi Mandal
A31: TXN5620 | B31: May 24, 2023 | C31: C2078 | D31: P1051 | E31: S104 | F31: 3 | G31: 35310 | H31: 15 | I31: CC | J31: online | K31: Ria Hayer
A32: TXN5029 | B32: 30/06/2023 | D32: P1021 | E32: S106 | F32: 1 | G32: 177050 | H32: 5 | I32: Net Banking | J32: instore | K32: Azad Sani
A33: TXN5135 | B33: 20.11.2024 | C33: C2088 | D33: P1005 | E33: S103 | F33: 0 | G33: Rs. 81,210 | H33: 15 | I33: Debit Card | J33: In Store | K33: Reva Nadig
A34: TXN5058 | B34: 17-Jul-2025 | C34: C2104 | D34: P1025 | E34: S101 | F34: 2 | G34: 88420 | H34: -5 | I34: EMI | J34: In Store | K34: Yutika Sama
A35: TXN5935 | B35: 18-Jan-2024 | C35: C2117 | D35: P1039 | E35: S104 | F35: 1 | G35: 121920 | I35: EMI | J35: Web
A36: TXN5138 | B36: August 16, 2023 | C36: C2033 | D36: P1004 | E36: S107 | F36: 0 | G36: ₹235,150.00 | H36: 10% | I36: COD | J36: online | K36: Gaurangi Sami
A37: TXN5035 | B37: 29/09/2023 | C37: C2064 | D37: P1045 | E37: S102 | F37: 3 | G37: ₹67,140.00 | H37: 0 | I37: CC | J37: IN-STORE | K37: Balendra Bali
A38: TXN5487 | B38: 26/11/2024 | C38: C2015 | D38: P1007 | E38: S106 | F38: 0 | G38: ₹48,190.00 | H38: 10% | I38: Net Banking | J38: online
A39: TXN5817 | B39: 11/21/2023 | C39: C2026 | D39: P1059 | E39: S102 | F39: -1 | G39: 80980 | H39: 5 | I39: cash | J39: IN-STORE | K39: Saumya Raja
A40: TXN5732 | B40: 10.06.2025 | C40: C2021 | D40: P1010 | E40: S101 | F40: 3 | G40: 237260 | H40: 15 | I40: Debit Card | J40: in-store | K40: Dayita Sankaran
A41: TXN5796 | B41: 28-Dec-2024 | D41: P1034 | E41: S105 | F41: 1 | G41: 84670 | H41: 5 | I41: Net Banking | J41: in-store | K41: Eta Naidu
A42: TXN5106 | B42: 2023-09-14 | C42: C2051 | D42: P1047 | E42: S108 | F42: 3 | G42: 91860 | H42: 10 | I42: Credit_Card | J42: ONLINE
A43: TXN5103 | B43: 14/08/2023 | C43: C2101 | D43: P1051 | E43: S105 | F43: 1 | G43: 77320 | H43: 10% | I43: CREDIT CARD | J43: online
A44: TXN5240 | B44: 04-Feb-2024 | C44: C2068 | D44: P1010 | E44: S107 | F44: 1 | G44: 75040 | I44: EMI | J44: online | K44: Christopher Bobal
A45: TXN5227 | B45: 06.08.2024 | C45: C2078 | D45: P1059 | E45: S107 | F45: 3 | G45: 247610 | I45: Debit Card | J45: Web | K45: Atharv Mane
A46: TXN5539 | B46: 02.04.2024 | C46: C2124 | D46: P1053 | E46: S102 | F46: 1 | G46: 146150 | H46: 15 | I46: Debit Card | J46: In Store | K46: Warhi Pathak
A47: TXN5553 | B47: 31/10/2024 | C47: C2042 | D47: P1021 | E47: S106 | F47: 0 | G47: 197,200.00 | H47: 10% | I47: Net Banking | J47: online
A48: TXN5490 | B48: March 24, 2025 | C48: C2047 | D48: P1025 | E48: S108 | F48: -1 | G48: ₹77,400.00 | H48: 10% | I48: CREDIT CARD | J48: in-store | K48: Charita Chakraborty
A49: TXN5228 | B49: 2023-02-24 | C49: C2145 | D49: P1053 | E49: S106 | F49: 1 | G49: 215870 | H49: 10 | I49: COD | J49: instore | K49: Meera Prakash
A50: TXN5175 | B50: 2023-11-04 | C50: C2148 | D50: P1026 | E50: S104 | F50: 1 | G50: 182000 | H50: 5 | I50: COD | J50: Web
A51: TXN5860 | B51: 24/04/2024 | C51: C2034 | D51: P1049 | E51: S108 | F51: 3 | G51: 154150 | H51: 0 | I51: EMI | J51: online
A52: TXN5454 | B52: 03/12/2023 | C52: C2072 | D52: P1021 | E52: S101 | F52: -1 | G52: 163,420.00 | H52: 0 | I52: Debit Card | J52: In Store | K52: Ishwar Chaudhary
A53: TXN5367 | B53: 29/08/2023 | C53: C2144 | D53: P1004 | E53: S101 | F53: 3 | G53: 220700 | H53: 5 | I53: Debit Card | J53: Web
A54: TXN5313 | B54: May 02, 2024 | C54: C2041 | D54: P1033 | E54: S101 | F54: -1 | G54: 68790 | I54: Net Banking | J54: instore | K54: Neel Mani
A55: TXN5007 | B55: 07/06/2024 | C55: C2040 | D55: P1035 | E55: S106 | F55: -1 | G55: 148260 | H55: 0 | I55: UPI | J55: In Store | K55: Meghana Sarma
A56: TXN5752 | B56: 12-Mar-2025 | C56: C2067 | D56: P1057 | E56: S102 | F56: 1 | G56: 111880 | H56: 0 | I56: Upi | J56: Web
A57: TXN5057 | B57: June 03, 2023 | C57: C2062 | D57: P1058 | E57: S101 | F57: -1 | G57: 166490 | H57: 0 | I57: EMI | J57: instore | K57: Baljiwan Sharma
A58: TXN5089 | B58: 19/11/2024 | C58: C2046 | D58: P1033 | E58: S106 | F58: 1 | G58: 191150 | I58: EMI | J58: in-store | K58: Radhika Roy
A59: TXN5360 | B59: 26/10/2024 | C59: C2062 | D59: P1028 | E59: S104 | F59: 1 | G59: 78030 | H59: -5 | I59: cash | J59: ONLINE | K59: Hamsini Murty
A60: TXN5740 | B60: 05.09.2024 | C60: C2082 | D60: P1007 | E60: S104 | F60: 2 | G60: 8,450.00 | H60: 0 | I60: Net Banking | J60: IN-STORE | K60: Vritti Sharma
A61: TXN5915 | B61: 30.05.2025 | C61: C2038 | D61: P1039 | E61: S106 | F61: 1 | G61: 213370 | H61: 10 | I61: EMI | J61: online | K61: Fariq Memon
A62: TXN5917 | B62: 04/30/2023 | C62: C2096 | D62: P1036 | E62: S107 | F62: -1 | G62: 57890 | I62: EMI | J62: online
A63: TXN5289 | B63: June 07, 2025 | C63: C2086 | D63: P1005 | E63: S107 | F63: 1 | G63: 5630 | H63: 15 | I63: cash | J63: In Store | K63: Chasmum Chahal
A64: TXN5877 | B64: 23/01/2025 | C64: C2137 | D64: P1001 | E64: S105 | F64: 2 | G64: ₹189,560.00 | H64: 0 | I64: CASH | J64: online
A65: TXN5165 | B65: 05.03.2025 | C65: C2131 | D65: P1025 | E65: S103 | F65: 1 | G65: 156450 | H65: 10 | I65: UPI | J65: online
A66: TXN5442 | B66: 06/04/2024 | C66: C2065 | D66: P1014 | E66: S101 | F66: 0 | G66: 10570 | H66: -5 | I66: CASH | J66: In Store | K66: Jai Wali
A67: TXN5882 | B67: 28/04/2024 | C67: C2070 | D67: P1022 | E67: S104 | F67: 1 | G67: Rs. 126,340 | H67: 15 | I67: Debit Card | J67: IN-STORE | K67: Aadhya Pall
A68: TXN5300 | B68: 07/19/2025 | C68: C2012 | D68: P1005 | E68: S105 | F68: 1 | G68: 189620 | H68: 10 | I68: Net Banking | J68: Web
A69: TXN5105 | B69: 09/23/2024 | C69: C2050 | D69: P1008 | E69: S103 | F69: 1 | G69: 213440 | H69: -5 | I69: EMI | J69: in-store | K69: Arunima Goda
A70: TXN5256 | B70: 10.04.2025 | C70: C2103 | D70: P1021 | E70: S102 | F70: 1 | G70: 83110 | H70: 10 | I70: CREDIT CARD | J70: in-store | K70: Vamakshi Loyal
A71: TXN5324 | B71: 03/27/2025 | C71: C2120 | D71: P1032 | E71: S107 | F71: -1 | G71: ₹163,140.00 | H71: 5 | I71: upi | J71: Web | K71: Harrison Sagar
A72: TXN5102 | B72: 03/16/2023 | C72: C2130 | D72: P1007 | E72: S105 | F72: 2 | G72: 153,220.00 | H72: -5 | I72: CASH | J72: online
A73: TXN5944 | B73: April 10, 2024 | C73: C2011 | D73: P1053 | E73: S105 | F73: -1 | G73: ₹53,000.00 | I73: EMI | J73: online
A74: TXN5047 | B74: 28.01.2024 | C74: C2126 | D74: P1037 | E74: S108 | F74: 1 | G74: 46360 | I74: CC | J74: In Store | K74: Ekani Bhat
A75: TXN5739 | B75: February 16, 2023 | C75: C2103 | D75: P1059 | E75: S103 | F75: 2 | G75: 71080 | H75: 0 | I75: COD | J75: Web
A76: TXN5133 | B76: 30-Jul-2024 | C76: C2063 | D76: P1049 | E76: S106 | F76: 0 | G76: 171670 | H76: 0 | I76: cash | J76: in-store | K76: Chameli Kade
A77: TXN5287 | B77: 03-Jan-2025 | C77: C2095 | D77: P1025 | E77: S106 | F77: 1 | G77: 74020 | H77: -5 | I77: Net Banking | J77: online | K77: Triveni Ravel
A78: TXN5097 | B78: 15.07.2025 | C78: C2063 | D78: P1021 | E78: S101 | F78: 3 | G78: 97820 | H78: 0 | I78: CASH | J78: in-store | K78: Dayita Shetty
A79: TXN5036 | B79: 20-Jun-2023 | C79: C2128 | D79: P1057 | E79: S107 | F79: 3 | G79: ₹138,320.00 | H79: -5 | I79: Net Banking | J79: online
A80: TXN5579 | B80: 2024-05-17 | C80: C2106 | D80: P1005 | E80: S108 | F80: 1 | G80: 55730 | H80: 10% | I80: EMI | J80: ONLINE
A81: TXN5828 | B81: 2024-09-16 | C81: C2092 | D81: P1038 | E81: S102 | F81: 1 | G81: 155010 | H81: 5 | I81: EMI | J81: ONLINE | K81: Arunima Nadkarni
A82: TXN5326 | B82: 11-Jul-2025 | C82: C2094 | D82: P1043 | E82: S102 | F82: -1 | G82: 236020 | H82: 5 | I82: Debit Card | J82: Web
A83: TXN5147 | B83: 03/10/2025 | D83: P1034 | E83: S108 | F83: -1 | G83: 45160 | H83: 5 | I83: EMI | J83: in-store | K83: Ekaja Seth
A84: TXN5412 | B84: 20-Apr-2024 | C84: C2026 | D84: P1022 | E84: S101 | F84: 0 | G84: 131230 | H84: 0 | I84: credit card | J84: ONLINE | K84: Banjeet Virk
A85: TXN5849 | B85: 14/09/2023 | C85: C2090 | D85: P1030 | E85: S104 | F85: 1 | G85: Rs. 100,260 | H85: 15 | I85: Net Banking | J85: ONLINE | K85: Saksham Magar
A86: TXN5701 | B86: May 10, 2023 | D86: P1042 | E86: S107 | F86: 3 | G86: 145610 | H86: 15 | I86: EMI | J86: ONLINE
A87: TXN5094 | B87: 05-Dec-2023 | C87: C2040 | D87: P1003 | E87: S103 | F87: 3 | G87: 150830 | H87: 15 | I87: COD | J87: in-store | K87: William Comar
A88: TXN5161 | B88: 10/02/2024 | C88: C2003 | D88: P1003 | E88: S108 | F88: 1 | G88: ₹95,360.00 | H88: 5 | I88: cash | J88: in-store | K88: Abha Dixit
A89: TXN5290 | B89: 24/07/2023 | C89: C2098 | D89: P1019 | E89: S108 | F89: 1 | G89: 206,410.00 | H89: 15 | I89: COD | J89: In Store | K89: Krishna Atwal
A90: TXN5370 | B90: February 19, 2025 | C90: C2129 | D90: P1047 | E90: S102 | F90: 1 | G90: 163,180.00 | H90: 5 | I90: CREDIT CARD | J90: IN-STORE | K90: Rudra Mitra
A91: TXN5195 | B91: 2024-06-17 | C91: C2117 | D91: P1030 | E91: S101 | F91: 2 | G91: 131600 | H91: 0 | I91: Net Banking | J91: ONLINE
A92: TXN5772 | B92: 01/03/2025 | C92: C2076 | D92: P1054 | E92: S106 | F92: 1 | G92: 83170 | H92: 10% | I92: Net Banking | J92: online | K92: Arya Edwin
A93: TXN5585 | B93: July 24, 2023 | C93: C2091 | D93: P1024 | E93: S102 | F93: 0 | G93: ₹45,140.00 | H93: 15 | I93: Net Banking | J93: instore | K93: Jonathan Upadhyay
A94: TXN5835 | B94: June 08, 2023 | C94: C2087 | D94: P1006 | E94: S108 | F94: -1 | G94: 196880 | H94: 0 | I94: upi | J94: In Store | K94: Yuvraj Kapadia
A95: TXN5705 | B95: 16.05.2024 | C95: C2065 | D95: P1044 | E95: S102 | F95: -1 | G95: Rs. 164,410 | H95: 10% | I95: COD | J95: IN-STORE | K95: Eshana Bajaj
A96: TXN5456 | B96: 13/03/2023 | C96: C2014 | D96: P1041 | E96: S103 | F96: 2 | G96: Rs. 34,890 | H96: 10 | I96: Debit Card | J96: IN-STORE | K96: Aadhya Chakraborty
A97: TXN5016 | B97: 17/04/2023 | C97: C2137 | D97: P1016 | E97: S107 | F97: 0 | G97: 240450 | H97: 5 | I97: EMI | J97: online | K97: Manan Sha
A98: TXN5673 | B98: 2025-04-22 | C98: C2095 | D98: P1014 | E98: S105 | F98: -1 | G98: 184090 | H98: -5 | I98: upi | J98: online | K98: Aryan Gola
A99: TXN5098 | B99: July 22, 2025 | C99: C2096 | D99: P1033 | E99: S108 | F99: 0 | G99: 14790 | H99: 10 | I99: UPI | J99: online
A100: TXN5669 | B100: August 26, 2024 | C100: C2022 | D100: P1010 | E100: S101 | F100: 3 | G100: 169780 | H100: 10% | I100: cash | J100: in-store | K100: Shravya Sibal
...

Sheet Raw_Products
A1: ProductID | B1: ProductName | C1: Category | D1: Material | E1: Purity | F1: Weight_g | G1: CostPrice | H1: SellingPrice | I1: StockQty | J1: Supplier | K1: LaunchDate
A2: P1001 | B2: Gold Ring #1 | C2: Rings | D2: Gold | E2: 24K | F2: 13.46 | G2: 55220 | H2: 79770 | I2: 84 | J2: Silver Line Exports | K2: January 02, 2024
A3: P1002 | B3: Rose Gold Anklet #2 | C3: Anklets | D3: rose gold | E3: 18K | F3: 21.04 | G3: 89440 | H3: 133960 | I3: 95 | J3: Diamond Hub Inc | K3: 23.11.2019
A4: P1003 | B4: Platinum Bangle #3 | C4: Bangles | D4: platinum | E4: 950 Platinum | F4: 33.24 | G4: 164,470.00 | H4: ₹253,160.00 | I4: 46 | J4: Rajesh Jewels Pvt Ltd | K4: 02/04/2022
A5: P1004 | B5: Silver Necklace #4 | C5: necklaces | D5: Silver | E5: 999 Silver | F5: 13.59 | G5: 70890 | H5: 91870 | I5: 45 | J5: Sundari Gems | K5: 05.03.2020
A6: P1005 | B6: Rose Gold Bracelet #5 | C6: bracelets | D6: Rose Gold | E6: 22K | F6: 38.16 | G6: 213510 | H6: 265100 | I6: 2 | J6: Diamond Hub Inc | K6: 08-Oct-2020
A7: P1006 | B7: Diamond Earring #6 | C7: Earrings | D7: diamond | E7: Platinum + Diamond | F7: 7.57 | G7: ₹41,720.00 | H7: ₹56,970.00 | I7: 93 | J7: Kundan Creations | K7: May 27, 2021
A8: P1007 | B8: Silver Anklet #7 | C8: Anklets | D8: silver | E8: 925 Silver | F8: 18.24 | G8: ₹93,190.00 | H8: 124620 | I8: 30 | J8: Kundan Creations | K8: 2023-10-29
A9: P1008 | B9: Platinum Earring #8 | C9: EARRINGS | D9: Platinum | E9: 950 Platinum | F9: 39.37 | G9: 169520 | H9: 238270 | I9: 75 | J9: GoldCraft Traders | K9: 11/10/2019
A10: P1009 | B10: Silver Ring #9 | C10: RINGS | D10: SILVER | E10: 925 Silver | F10: 39.69 | G10: 240390 | H10: 284680 | I10: 60 | J10: Diamond Hub Inc | K10: May 22, 2019
A11: P1010 | B11: Rose Gold Bracelet #10 | D11: ROSE GOLD | E11: 22K | F11: 18.86 | G11: ₹100,210.00 | H11: 130210 | I11: 113 | J11: Kundan Creations | K11: 2021-07-13
A12: P1011 | B12: Gold Bracelet #11 | C12: BRACELETS | D12: GOLD | E12: 18K | F12: 40.89 | G12: 238020 | H12: 280470 | I12: 28 | J12: Sundari Gems | K12: 02-Oct-2022
A13: P1012 | B13: Gold Necklace #12 | C13: Necklaces | D13: Gold | E13: 24K | F13: 20.25 | G13: Rs. 94,030 | H13: 125700 | I13: 91 | J13: Rajesh Jewels Pvt Ltd | K13: 11.10.2022
A14: P1013 | B14: Diamond Earring #13 | C14: Earrings | E14: Platinum + Diamond | F14: 21.62 | G14: 126720 | H14: Rs. 149,550 | I14: 101 | J14: Diamond Hub Inc | K14: October 20, 2023
A15: P1014 | B15: Diamond Nose Pin #14 | C15: Nose Pins | D15: diamond | E15: Platinum + Diamond | F15: 10.8 | G15: 49490 | H15: Rs. 58,070 | I15: 46 | J15: Rajesh Jewels Pvt Ltd | K15: 03/10/2021
A16: P1015 | B16: Platinum Bracelet #15 | C16: Bracelets | D16: PLATINUM | E16: 950 Platinum | F16: 26.69 | G16: ₹132,490.00 | H16: 192000 | I16: 5 | J16: Rajesh Jewels Pvt Ltd | K16: 11-Apr-2022
A17: P1016 | B17: Diamond Necklace #16 | C17: necklaces | D17: diamond | E17: 18K Gold + Diamond | F17: 26.68 | G17: 96240 | H17: 113,830.00 | I17: 82 | J17: Kundan Creations | K17: March 03, 2022
A18: P1017 | B18: Platinum Necklace #17 | C18: necklaces | D18: PLATINUM | E18: 950 Platinum | F18: 21.44 | G18: Rs. 132,840 | H18: 205690 | I18: 7 | J18: Kundan Creations | K18: March 12, 2020
A19: P1018 | B19: Platinum Ring #18 | C19: Ring | D19: PLATINUM | E19: 950 Platinum | F19: 42.03 | G19: 158860 | H19: 238,490.00 | I19: 31 | J19: Rajesh Jewels Pvt Ltd | K19: 2023-12-28
A20: P1019 | B20: Diamond Bangle #19 | C20: bangles | D20: DIAMOND | E20: 18K Gold + Diamond | G20: ₹25,590.00 | H20: 32260 | I20: -2 | J20: Sundari Gems | K20: 29/04/2023
A21: P1020 | B21: Silver Ring #20 | C21: rings | D21: SILVER | E21: 999 Silver | F21: 26.84 | G21: 104670 | H21: 125710 | I21: 37 | J21: Sundari Gems | K21: 2024-01-16
A22: P1021 | B22: Silver Bracelet #21 | C22: Bracelets | D22: SILVER | E22: 925 Silver | F22: 43.96 | G22: 250090 | H22: Rs. 375,780 | I22: 1 | J22: GoldCraft Traders | K22: 02/17/2023
A23: P1022 | B23: Diamond Pendant #22 | C23: pendants | D23: Diamond | E23: Platinum + Diamond | F23: 37.19 | G23: 217660 | H23: 269720 | I23: 82 | J23: GoldCraft Traders | K23: 03/27/2021
A24: P1023 | B24: Gold Necklace #23 | C24: necklaces | D24: Gold | E24: 22K | F24: 9.27 | G24: 56,540.00 | H24: 71020 | I24: 11 | J24: Kundan Creations | K24: 06/08/2021
A25: P1024 | B25: Gold Bracelet #24 | C25: bracelets | D25: gold | E25: 22K | F25: 20.26 | G25: Rs. 122,820 | H25: 186480 | I25: 77 | J25: Sundari Gems | K25: 2022-09-20
A26: P1025 | B26: Diamond Earring #25 | C26: Earrings | D26: diamond | E26: Platinum + Diamond | F26: 19.16 | G26: 110190 | H26: 140110 | I26: 24 | J26: Malabar Suppliers | K26: May 29, 2023
A27: P1026 | B27: Silver Necklace #26 | C27: necklaces | D27: SILVER | E27: 999 Silver | F27: 23.92 | G27: 124600 | H27: 160000 | I27: 102 | J27: Diamond Hub Inc | K27: 26.04.2020
A28: P1027 | B28: Diamond Anklet #27 | C28: Anklets | D28: Diamond | E28: 18K Gold + Diamond | F28: 32.75 | G28: 148580 | H28: 194620 | I28: 16 | J28: Silver Line Exports | K28: 2022-11-09
A29: P1028 | B29: Gold Nose Pin #28 | C29: Nose Pins | D29: Gold | E29: 18K | F29: 36.36 | G29: 192800 | H29: 297,910.00 | I29: 74 | J29: Sundari Gems | K29: 29-Apr-2024
A30: P1029 | B30: Silver Bangle #29 | C30: bangles | D30: Silver | E30: 999 Silver | F30: 28.76 | G30: ₹121,980.00 | H30: 144060 | I30: 34 | J30: GoldCraft Traders | K30: 07/10/2020
A31: P1030 | B31: Rose Gold Nose Pin #30 | C31: Nose Pins | D31: Rose Gold | E31: 22K | F31: 4.21 | G31: 24200 | H31: 31600 | I31: 96 | J31: Kundan Creations | K31: 21.04.2024
A32: P1031 | B32: Rose Gold Bracelet #31 | C32: BRACELETS | D32: Rose Gold | E32: 22K | F32: 11.04 | G32: 51630 | H32: 59970 | I32: 41 | J32: Silver Line Exports | K32: 22-Oct-2022
A33: P1032 | B33: Gold Anklet #32 | C33: anklets | D33: Gold | E33: 18K | F33: 39.21 | G33: 156470 | H33: 196220 | I33: 39 | J33: GoldCraft Traders | K33: 07/20/2021
A34: P1033 | B34: Gold Pendant #33 | C34: PENDANTS | D34: Gold | E34: 18K | F34: 29.78 | G34: 167050 | H34: 235660 | I34: 94 | J34: Rajesh Jewels Pvt Ltd | K34: 28/04/2024
A35: P1034 | B35: Platinum Pendant #34 | C35: Pendants | D35: Platinum | E35: 950 Platinum | F35: 27.86 | G35: 170000 | H35: Rs. 244,350 | I35: 97 | J35: Diamond Hub Inc | K35: 12/02/2019
A36: P1035 | B36: Rose Gold Bracelet #35 | C36: Bracelets | D36: rose gold | E36: 18K | F36: 31.83 | G36: ₹137,320.00 | H36: 195500 | I36: 101 | J36: Rajesh Jewels Pvt Ltd | K36: June 19, 2023
A37: P1036 | B37: Diamond Necklace #36 | C37: Necklaces | D37: diamond | E37: Platinum + Diamond | F37: 43.29 | G37: 225800 | H37: 334520 | I37: 88 | J37: GoldCraft Traders | K37: 10/06/2021
A38: P1037 | B38: Platinum Bracelet #37 | C38: bracelets | D38: Platinum | E38: 950 Platinum | F38: 13.63 | G38: 64,290.00 | H38: 93,230.00 | I38: 70 | J38: Kundan Creations | K38: 30-Sep-2022
A39: P1038 | B39: Rose Gold Bangle #38 | D39: Rose Gold | E39: 18K | F39: 23.97 | G39: Rs. 96,260 | H39: 119990 | I39: 50 | J39: Malabar Suppliers | K39: 11/02/2022
A40: P1039 | B40: Platinum Nose Pin #39 | C40: nose pins | D40: PLATINUM | E40: 950 Platinum | F40: 20.01 | G40: 110340 | H40: Rs. 141,490 | I40: 87 | J40: Malabar Suppliers | K40: 07/08/2020
A41: P1040 | B41: Silver Nose Pin #40 | C41: nose pins | D41: SILVER | E41: 999 Silver | F41: 33.02 | G41: ₹202,640.00 | H41: ₹275,560.00 | I41: 34 | J41: Rajesh Jewels Pvt Ltd | K41: 02/09/2023
A42: P1041 | B42: Platinum Earring #41 | C42: Earrings | D42: platinum | E42: 950 Platinum | F42: 5.96 | G42: ₹21,060.00 | H42: 26610 | I42: 59 | J42: Malabar Suppliers | K42: 28/11/2020
A43: P1042 | B43: Gold Earring #42 | C43: Earrings | D43: GOLD | E43: 18K | F43: 36.78 | G43: 222980 | H43: 264020 | I43: 29 | J43: Rajesh Jewels Pvt Ltd | K43: 16-Feb-2022
A44: P1043 | B44: Rose Gold Ring #43 | C44: RINGS | D44: Rose Gold | E44: 18K | F44: 42.72 | G44: ₹173,490.00 | H44: 214,160.00 | I44: 82 | J44: Rajesh Jewels Pvt Ltd | K44: 18/11/2019
A45: P1044 | B45: Platinum Nose Pin #44 | C45: Nose Pins | D45: Platinum | E45: 950 Platinum | F45: 31.4 | G45: ₹188,230.00 | H45: Rs. 275,780 | I45: 78 | J45: Kundan Creations | K45: 16/09/2022
A46: P1045 | B46: Platinum Bangle #45 | C46: Bangles | D46: Platinum | E46: 950 Platinum | F46: 6.91 | G46: 37,030.00 | H46: ₹52,950.00 | I46: 118 | J46: Sundari Gems | K46: October 21, 2021
A47: P1046 | B47: Rose Gold Ring #46 | C47: RINGS | D47: Rose Gold | E47: 22K | F47: 26.57 | G47: 147,740.00 | H47: 180250 | I47: 64 | J47: Silver Line Exports | K47: 06/24/2021
A48: P1047 | B48: Silver Pendant #47 | C48: Pendants | D48: Silver | E48: 999 Silver | F48: 31.67 | G48: 135490 | H48: 207040 | I48: 102 | J48: Diamond Hub Inc | K48: 2022-01-31
A49: P1048 | B49: Rose Gold Nose Pin #48 | C49: NOSE PINS | D49: rose gold | E49: 22K | F49: 3.86 | G49: ₹18,910.00 | H49: 26460 | I49: 61 | J49: Silver Line Exports | K49: 2021-06-24
A50: P1049 | B50: Rose Gold Bracelet #49 | C50: Bracelets | D50: Rose Gold | E50: 18K | F50: 15.02 | G50: 53120 | H50: 69760 | I50: 26 | J50: Diamond Hub Inc | K50: 2024-02-13
A51: P1050 | B51: Diamond Nose Pin #50 | C51: Nose Pins | D51: diamond | E51: 18K Gold + Diamond | F51: 21.37 | G51: 83,140.00 | H51: ₹101,950.00 | I51: 74 | J51: Kundan Creations | K51: 09/03/2023
A52: P1051 | B52: Platinum Nose Pin #51 | C52: nose pins | D52: PLATINUM | E52: 950 Platinum | F52: 20.92 | G52: 100580 | H52: 129,040.00 | I52: 95 | J52: Kundan Creations | K52: 11-Feb-2021
A53: P1052 | B53: Diamond Anklet #52 | C53: ANKLETS | D53: diamond | E53: Platinum + Diamond | F53: 44.5 | G53: 250960 | H53: 354060 | I53: 17 | J53: Malabar Suppliers | K53: 2024-05-29
A54: P1053 | B54: Diamond Earring #53 | C54: earrings | D54: Diamond | E54: 18K Gold + Diamond | F54: 21.92 | G54: 134080 | H54: 172350 | I54: 86 | J54: Malabar Suppliers | K54: 2022-08-23
A55: P1054 | B55: Silver Bangle #54 | C55: Bangles | D55: SILVER | E55: 925 Silver | F55: 33.98 | G55: 158,750.00 | H55: 188810 | I55: 79 | J55: Silver Line Exports | K55: 2023-11-23
A56: P1055 | B56: Silver Bracelet #55 | C56: Bracelets | D56: SILVER | E56: 999 Silver | F56: 26.12 | G56: 147310 | H56: 179420 | I56: 8 | J56: Kundan Creations | K56: 19-Nov-2023
A57: P1056 | B57: Diamond Bangle #56 | C57: bangles | D57: Diamond | E57: 18K Gold + Diamond | F57: 4.71 | G57: Rs. 28,510 | H57: 44050 | I57: 36 | J57: Silver Line Exports | K57: 24-May-2024
A58: P1057 | B58: Rose Gold Bangle #57 | C58: Bangles | D58: Rose Gold | E58: 22K | F58: 2.45 | G58: 14070 | H58: Rs. 18,410 | I58: -1 | J58: Kundan Creations | K58: 07.11.2023
A59: P1058 | B59: Silver Bangle #58 | C59: Bangles | D59: silver | E59: 925 Silver | F59: 28.83 | G59: Rs. 171,230 | H59: ₹241,180.00 | I59: 37 | J59: Diamond Hub Inc | K59: 2021-06-21
A60: P1059 | B60: Rose Gold Pendant #59 | C60: pendants | D60: Rose Gold | E60: 22K | F60: 37.63 | G60: 157810 | H60: 233540 | I60: 59 | J60: Diamond Hub Inc | K60: 27.08.2020
A61: P1060 | B61: Diamond Pendant #60 | C61: pendants | D61: Diamond | E61: 18K Gold + Diamond | F61: 35.89 | G61: ₹126,960.00 | H61: 173250 | I61: 56 | J61: Sundari Gems | K61: 09.10.2022
A62: P1006 | B62: Diamond Earring #6 | C62: Earrings | D62: diamond | E62: Platinum + Diamond | F62: 7.57 | G62: ₹41,720.00 | H62: ₹56,970.00 | I62: 93 | J62: Kundan Creations | K62: May 27, 2021
A63: P1021 | B63: Silver Bracelet #21 | C63: Bracelets | D63: SILVER | E63: 925 Silver | F63: 43.96 | G63: 250090 | H63: Rs. 375,780 | I63: 1 | J63: GoldCraft Traders | K63: 02/17/2023

Sheet Raw_Customers
A1: CustomerID | B1: CustomerName | C1: Gender | D1: Age | E1: City | F1: State | G1: Email | H1: Phone | I1: MembershipTier | J1: JoinDate
A2: C2001 | B2: Kritika Brar | C2: FEMALE | D2: 44 | E2: chennai | F2: Tamil Nadu | G2: bakshianvi@example.org | H2: 1960013389 | I2: Silver | J2: 17.03.2023
A3: C2002 | B3: Alka Dewan | C3: Female | D3: -5 | E3: Delhi | F3: Delhi | G3: janaki93@example.net | H3: +91-2832764835 | I3: Gold | J3: 11/01/2024
A4: C2003 | B4: Neel Zacharia | C4: m | D4: -5 | E4: Surat | F4: Gujarat | G4: adyasangha@example.net | H4: +91-8480184514 | I4: Platinum | J4: 2021-02-19
A5: C2004 | B5: Veer Bir | C5: M | D5: -5 | E5: Jaipur | F5: Rajasthan | G5: naikvrinda@example.org | H5: +91-8963834657 | I5: Silver | J5: 06-Sep-2018
A6: C2005 | B6: Girik Khalsa | C6: Male | E6: Hyderabad | F6: Telangana | G6: narayananekavir@example.net | H6: +91-6701065133 | I6: Silver | J6: May 31, 2019
A7: C2006 | B7: Finn Saini | C7: MALE | E7: Mumbay | F7: Maharashtra | G7: niharikasunder@example.com | H7: 6064746872 | I7: Gold | J7: 16/08/2019
A8: C2007 | B8: Samar Lalla | C8: female | D8: -5 | E8: Surat | F8: Gujarat | G8: advika35@example.org | H8: 7510799118 | I8: Silver | J8: 06/03/2018
A9: C2008 | B9: Gaurangi Sabharwal | C9: FEMALE | D9: 57 | E9: Surat | F9: Gujarat | G9: dkrishnamurthy@example.org | H9: 05869232260 | I9: Silver | J9: January 26, 2023
A10: C2009 | B10: Chaitanya Sarin | C10: Male | D10: -5 | E10: Ahmedabad | F10: Gujarat | H10: 3375433036 | I10: Silver | J10: 13.10.2022
A11: C2010 | B11: Girik Keer | C11: Male | D11: N/A | E11: BENGALURU | F11: Karnataka | G11: venkateshronith@example.com | H11: 07773872148 | I11: Gold | J11: 01.01.2025
A12: C2011 | B12: William Maharaj | C12: Female | D12: -5 | E12: Lucknow | F12: Uttar Pradesh | G12: umang32@example.org | I12: None | J12: 08.03.2024
A13: C2012 | B13: Lopa Nayar | C13: f | D13: N/A | E13: Pune | F13: Maharashtra | G13: tbrahmbhatt@example.com | I13: Silver | J13: 04-Jul-2021
A14: C2013 | B14: Udyati Kunda | C14: Male | D14: N/A | E14: Pune | F14: Maharashtra | G14: dgandhi@example.org | I14: Gold | J14: 07/03/2022
A15: C2014 | B15: Rajata Loyal | C15: Female | E15: Kolkata | F15: West Bengal | G15: oliver99@example.net | H15: +91-9058651850 | I15: Gold | J15: 2021-12-11
A16: C2015 | B16: Pavani Narayanan | C16: FEMALE | D16: 45 | E16: Hyderabad | F16: Telangana | G16: yatan14@example.com | H16: 01436349578 | I16: Silver | J16: February 15, 2021
A17: C2016 | B17: Ishaan Bhattacharyya | C17: F | D17: -5 | E17: Hyderabad | F17: Telangana | H17: 1823374989 | I17: None | J17: 26/01/2018
A18: C2017 | B18: Vincent Mani | C18: m | D18: N/A | E18: Pune | F18: Maharashtra | G18: eswamy@example.net | H18: 4131869993 | I18: Gold | J18: 28/10/2021
A19: C2018 | B19: Zilmil Sathe | C19: male | D19: -5 | E19: Surat | F19: Gujarat | G19: sudiksha13@example.com | I19: Gold | J19: 12/01/2018
A20: C2019 | B20: Ayush Khatri | C20: M | D20: N/A | E20: Pune | F20: Maharashtra | I20: Platinum | J20: 06.03.2021
A21: C2020 | B21: Tamanna Nagy | C21: Male | D21: N/A | E21: Chenai | F21: Tamil Nadu | G21: deepaatwal@example.net | I21: None | J21: 15/05/2020
A22: C2021 | B22: Guneet Chaudhry | C22: male | D22: N/A | E22: Pune | F22: Maharashtra | H22: 6627028951 | I22: None | J22: August 12, 2023
A23: C2022 | B23: Rushil Rajagopalan | C23: Female | D23: N/A | E23: Hyderabad | F23: Telangana | G23: sganesan@example.com | H23: 4556238692 | I23: Platinum | J23: 06-Jun-2024
A24: C2023 | B24: Chakrika Nigam | C24: MALE | D24: -5 | E24: Ahmedabad | F24: Gujarat | G24: pchhabra@example.com | H24: 0640909743 | I24: None | J24: 27-Dec-2018
A25: C2024 | B25: Oni Dubey | C25: F | E25: Chenai | F25: Tamil Nadu | G25: sidhufaqid@example.org | H25: 00471138267 | I25: Gold | J25: 2019-11-20
A26: C2025 | B26: Owen Choudhary | C26: male | D26: 27 | E26: Delhi | F26: Delhi | G26: fchaudhary@example.net | I26: Silver | J26: 14/11/2020
A27: C2026 | B27: Lakshmi Wali | C27: FEMALE | D27: -5 | E27: Coimbatore | F27: Tamil Nadu | G27: deepalexander@example.com | H27: 07711592124 | I27: Gold | J27: 18/07/2021
A28: C2027 | B28: Yashica Kala | C28: FEMALE | D28: N/A | E28: Delhi | F28: Delhi | H28: 6736576615 | I28: Silver | J28: 07-Mar-2023
A29: C2028 | B29: Charles Dugal | C29: f | D29: -5 | E29: Surat | F29: Gujarat | G29: vasatikakapur@example.org | H29: 4936899809 | I29: Platinum | J29: January 17, 2023
A30: C2029 | B30: Mekhala Basak | C30: Female | E30: Jaipur | F30: Rajasthan | G30: chandranbumb@example.com | H30: 07622683885 | I30: Platinum | J30: 10/06/2018
A31: C2030 | B31: Rudra Ghose | C31: FEMALE | D31: -5 | E31: Mumbay | F31: Maharashtra | G31: dbahl@example.org | H31: +91-3696816453 | I31: Silver | J31: 09/27/2018
A32: C2031 | B32: Yachana Dora | C32: M | D32: N/A | E32: Kolkata | F32: West Bengal | G32: faqidgoel@example.net | H32: 08679807935 | I32: Platinum | J32: June 13, 2019
A33: C2032 | B33: Joshua Vyas | C33: m | D33: N/A | E33: Jaipur | F33: Rajasthan | G33: seshadriharshil@example.com | I33: Silver | J33: 03/16/2018
A34: C2033 | B34: Triya Manda | C34: male | D34: 65 | E34: Delhi | F34: Delhi | G34: sampathyashoda@example.com | H34: +91-9622292706 | I34: None | J34: February 19, 2019
A35: C2034 | B35: Liam Singh | C35: male | E35: bengaluru | F35: Karnataka | G35: hthakkar@example.com | H35: 05305152204 | I35: Gold | J35: 2022-11-28
A36: C2035 | B36: Madhavi Singhal | C36: female | D36: N/A | E36: Jaipur | F36: Rajasthan | G36: fahluwalia@example.org | I36: None | J36: 21-Jun-2021
A37: C2036 | B37: Ria Raju | C37: f | D37: N/A | E37: Jaipur | F37: Rajasthan | I37: None | J37: 26/10/2019
A38: C2037 | B38: Leela Bali | C38: MALE | E38: Delhi | F38: Delhi | G38: rachit77@example.com | H38: 6928451154 | I38: Silver | J38: 10/12/2018
A39: C2038 | B39: Jairaj Iyer | C39: m | E39: Hyderabad | F39: Telangana | G39: shivaniprabhakar@example.com | H39: 8565431027 | I39: Gold | J39: 2022-08-27
A40: C2039 | B40: Farhan Krishna | C40: M | E40: Delhi | F40: Delhi | G40: warjastak@example.org | I40: Silver | J40: 22/08/2019
A41: C2040 | B41: Maanas Munshi | C41: Male | D41: -5 | E41: Mumbay | F41: Maharashtra | G41: anvidass@example.net | H41: 04710276773 | I41: Gold | J41: 02/06/2020
A42: C2041 | B42: Bhavika Yadav | C42: Male | D42: 49 | E42: Chennai | F42: Tamil Nadu | G42: hemani62@example.com | H42: +91-9532787747 | I42: Silver | J42: 26-Dec-2024
A43: C2042 | B43: Manthan Varma | C43: f | D43: 29 | E43: Mumbai | F43: Maharashtra | G43: chokshiraagini@example.org | H43: 08680002578 | I43: Gold | J43: 16/12/2021
A44: C2043 | B44: Max Sachar | C44: m | D44: N/A | E44: Ahmedabad | F44: Gujarat | G44: falaknagar@example.org | H44: 06230913075 | I44: Silver | J44: 05/04/2022
A45: C2044 | B45: Bina Basak | C45: MALE | E45: Lucknow | F45: Uttar Pradesh | G45: nirjathaker@example.net | I45: Gold | J45: 2019-07-01
A46: C2045 | B46: Patrick Bansal | C46: female | E46: Bangalore | F46: Karnataka | G46: farhan57@example.net | H46: 04540193802 | I46: Silver | J46: 2023-02-18
A47: C2046 | B47: Advika Rajagopal | C47: FEMALE | D47: 40 | E47: Ahmedabad | F47: Gujarat | G47: ltandon@example.net | H47: 08516122753 | I47: Silver | J47: 30.05.2018
A48: C2047 | B48: Mason Gala | C48: f | D48: -5 | E48: Pune | F48: Maharashtra | G48: sanyaloke@example.com | H48: 09187851910 | I48: None | J48: 05/03/2022
A49: C2048 | B49: Kiaan Pall | C49: Female | D49: N/A | E49: Pune | F49: Maharashtra | G49: zinal71@example.net | H49: 04622656766 | I49: Silver | J49: 02/13/2024
A50: C2049 | B50: Eiravati Nagi | C50: female | D50: -5 | E50: Lucknow | F50: Uttar Pradesh | G50: gokhalemaya@example.net | H50: 4786863375 | I50: Silver | J50: 10-Dec-2021
A51: C2050 | B51: George Wason | C51: F | D51: -5 | E51: Jaipur | F51: Rajasthan | H51: 0892687056 | I51: None | J51: 08/05/2018
A52: C2051 | B52: Madhav Babu | C52: F | D52: N/A | E52: Pune | F52: Maharashtra | G52: charanloyal@example.com | H52: 8373540331 | I52: Platinum | J52: 14/10/2024
A53: C2052 | B53: Nisha Arora | C53: f | D53: -5 | E53: Hyderabad | F53: Telangana | G53: omisha42@example.org | H53: 3785477725 | I53: Silver | J53: 2020-10-19
A54: C2053 | B54: Victor Kakar | C54: f | D54: -5 | E54: Chenai | F54: Tamil Nadu | G54: wagleanvi@example.net | I54: Silver | J54: 05/07/2023
A55: C2054 | B55: Rachana Grewal | C55: F | E55: Lucknow | F55: Uttar Pradesh | G55: cmadan@example.org | H55: +91-5621850163 | I55: Silver | J55: March 02, 2024
A56: C2055 | B56: Xavier Verma | C56: Male | D56: N/A | E56: CHENNAI | F56: Tamil Nadu | G56: xchada@example.net | H56: +91-1212678886 | I56: Silver | J56: 27-Aug-2020
A57: C2056 | B57: Eiravati Manne | C57: Male | D57: 44 | E57: Kolkata | F57: West Bengal | G57: lajitagara@example.org | H57: 06924593752 | I57: Gold | J57: May 15, 2023
A58: C2057 | B58: Ojas Basu | C58: f | E58: Coimbatore | F58: Tamil Nadu | G58: ukibe@example.com | H58: 9398280737 | I58: Gold | J58: June 10, 2019
A59: C2058 | B59: Ishwar Bajaj | C59: M | D59: N/A | E59: bengaluru | F59: Karnataka | G59: ynarula@example.com | H59: 08757177514 | I59: Silver | J59: 14.08.2021
A60: C2059 | B60: Ijaya Pandey | C60: female | E60: Coimbatore | F60: Tamil Nadu | G60: ikbal23@example.net | H60: +91-6033419182 | I60: Silver | J60: November 21, 2024
A61: C2060 | B61: Nilima Swamy | C61: FEMALE | D61: N/A | E61: mumbai | F61: Maharashtra | G61: rgera@example.net | I61: None | J61: 2018-11-29
A62: C2061 | B62: Liam Jhaveri | C62: m | D62: -5 | E62: Coimbatore | F62: Tamil Nadu | G62: fsawhney@example.org | H62: 4043842797 | I62: Silver | J62: 22-May-2021
A63: C2062 | B63: Dev Warrior | C63: m | D63: N/A | E63: Pune | F63: Maharashtra | G63: danielpanchal@example.net | H63: 08457759017 | I63: Silver | J63: 18/03/2023
A64: C2063 | B64: Faras Deo | C64: f | D64: -5 | E64: BENGALURU | F64: Karnataka | G64: bkamdar@example.org | I64: Silver | J64: October 11, 2023
A65: C2064 | B65: Yug Malhotra | C65: Male | D65: N/A | E65: Kolkata | F65: West Bengal | G65: zilmilsaxena@example.org | H65: 03112196565 | I65: Silver | J65: 25-Nov-2024
A66: C2065 | B66: Pallavi Ratti | C66: m | D66: -5 | E66: Jaipur | F66: Rajasthan | G66: kotharibhavani@example.net | H66: +91-8055269658 | I66: Gold | J66: 08/05/2023
A67: C2066 | B67: Anita Viswanathan | C67: Female | D67: -5 | E67: Mumbay | F67: Maharashtra | G67: yadavmichael@example.com | H67: 3285691463 | I67: None | J67: July 21, 2023
A68: C2067 | B68: Nandini Biswas | C68: female | E68: Kolkata | F68: West Bengal | G68: lallfaraj@example.com | H68: 04195180238 | I68: Silver | J68: 07/10/2022
A69: C2068 | B69: Kashish Shanker | C69: FEMALE | D69: N/A | E69: Kolkata | F69: West Bengal | G69: xmandal@example.com | H69: 08367024103 | I69: Gold | J69: 2019-06-12
A70: C2069 | B70: Tanveer Narang | C70: MALE | D70: N/A | E70: Jaipur | F70: Rajasthan | G70: chandranyashasvi@example.org | I70: Silver | J70: 2023-08-11
A71: C2070 | B71: Megha Taneja | C71: M | D71: N/A | E71: Surat | F71: Gujarat | G71: gavinkothari@example.com | I71: None | J71: 28-Oct-2019
A72: C2071 | B72: Ayushman Mand | C72: f | D72: N/A | E72: Mumbay | F72: Maharashtra | G72: rajapooja@example.org | H72: 4720999347 | I72: Silver | J72: 18.09.2021
A73: C2072 | B73: Kalpit Oak | C73: FEMALE | D73: -5 | E73: Surat | F73: Gujarat | G73: sodhiishita@example.net | H73: +91-9059929378 | I73: Gold | J73: July 30, 2018
A74: C2073 | B74: Watika Dhaliwal | C74: male | E74: Bombay | F74: Maharashtra | G74: ekiyabhargava@example.org | I74: Silver | J74: 08-Jul-2021
A75: C2074 | B75: Girik Nigam | C75: male | D75: -5 | E75: Jaipur | F75: Rajasthan | G75: faras35@example.com | H75: +91-6765861793 | I75: None | J75: 04/16/2024
A76: C2075 | B76: Vrinda Lanka | C76: FEMALE | D76: N/A | E76: Hyderabad | F76: Telangana | G76: bbalasubramanian@example.net | H76: +91-6987205061 | I76: Silver | J76: 03-Nov-2024
A77: C2076 | B77: Oliver Kakar | C77: F | D77: N/A | E77: Lucknow | F77: Uttar Pradesh | G77: ramqasim@example.com | I77: Gold | J77: 06/26/2023
A78: C2077 | B78: Orinder Majumdar | C78: F | D78: N/A | E78: BENGALURU | F78: Karnataka | G78: jonathanbasak@example.com | H78: 04856467997 | I78: None | J78: 06/22/2018
A79: C2078 | B79: Oscar Hans | C79: male | E79: Jaipur | F79: Rajasthan | G79: ndhawan@example.net | H79: +91-4754691373 | I79: Silver | J79: 21.04.2024
A80: C2079 | B80: Udarsh Krishnan | C80: Male | D80: 26 | E80: Pune | F80: Maharashtra | G80: dalbirkrish@example.org | H80: +91-8552414060 | I80: Platinum | J80: 2023-04-19
A81: C2080 | B81: Hemal Kapadia | C81: f | D81: 21 | E81: Coimbatore | F81: Tamil Nadu | G81: anvi66@example.com | H81: +91-1545444328 | I81: Silver | J81: 03/22/2021
A82: C2081 | B82: Tanvi Dhar | C82: male | D82: N/A | E82: Pune | F82: Maharashtra | G82: gparmer@example.com | H82: 1724825135 | I82: None | J82: 29-May-2018
A83: C2082 | B83: Chakradev Misra | C83: M | D83: -5 | E83: Kolkata | F83: West Bengal | G83: pranit17@example.com | H83: 7432927129 | I83: Gold | J83: February 04, 2024
A84: C2083 | B84: Osha Chaudhuri | C84: F | E84: Lucknow | F84: Uttar Pradesh | G84: tamanna89@example.net | I84: Silver | J84: 27.02.2018
A85: C2084 | B85: Bina Parsa | C85: Female | D85: 33 | E85: Pune | F85: Maharashtra | G85: laksh61@example.net | H85: +91-3753001197 | I85: Gold | J85: 27/01/2020
A86: C2085 | B86: Chakradhar Bhatnagar | C86: F | D86: 33 | E86: Kolkata | F86: West Bengal | G86: pooja11@example.org | I86: Gold | J86: 07.12.2020
A87: C2086 | B87: Widisha Badami | C87: FEMALE | D87: N/A | E87: Lucknow | F87: Uttar Pradesh | G87: dipta08@example.net | H87: +91-7721753540 | I87: None | J87: 26.04.2019
A88: C2087 | B88: Tanvi Halder | C88: female | E88: Ahmedabad | F88: Gujarat | G88: ravalnitara@example.org | H88: 4883755037 | I88: Gold | J88: 31.08.2022
A89: C2088 | B89: Sai Kadakia | C89: Female | E89: Surat | F89: Gujarat | G89: hritik60@example.net | I89: None | J89: September 10, 2018
A90: C2089 | B90: Omaja Munshi | C90: MALE | E90: Ahmedabad | F90: Gujarat | G90: hemani22@example.net | I90: None | J90: 22-Sep-2023
A91: C2090 | B91: Qarin Verma | C91: F | E91: Lucknow | F91: Uttar Pradesh | G91: aryazayan@example.org | H91: 8933472122 | I91: None | J91: 06/10/2022
A92: C2091 | B92: Oliver Yogi | C92: MALE | E92: mumbai | F92: Maharashtra | G92: tiwarinathaniel@example.com | I92: Silver | J92: 2023-04-18
A93: C2092 | B93: Gabriel Manda | C93: f | E93: Pune | F93: Maharashtra | G93: bhattishivansh@example.net | H93: 00919015814 | I93: None | J93: 25.11.2018
A94: C2093 | B94: Elijah Mannan | C94: FEMALE | D94: -5 | E94: bengaluru | F94: Karnataka | G94: zraj@example.net | H94: +91-9968814353 | I94: None | J94: 2018-01-15
A95: C2094 | B95: Avni Dey | C95: female | D95: 44 | E95: Kolkata | F95: West Bengal | G95: krishnaguneet@example.org | H95: 3149135775 | I95: None | J95: 2019-04-08
A96: C2095 | B96: Theodore Sura | C96: m | E96: Surat | F96: Gujarat | G96: adyabose@example.net | H96: 9969308488 | I96: Silver | J96: 29.09.2020
A97: C2096 | B97: Siddharth Doctor | C97: female | D97: N/A | E97: Lucknow | F97: Uttar Pradesh | G97: devlalla@example.com | H97: +91-2665918463 | I97: None | J97: June 23, 2024
A98: C2097 | B98: Qabil Vaidya | C98: m | E98: Kolkata | F98: West Bengal | G98: nakulpathak@example.net | I98: None | J98: September 07, 2018
A99: C2098 | B99: Krish Kumar | C99: M | E99: Coimbatore | F99: Tamil Nadu | G99: oliver57@example.net | H99: +91-0881172980 | I99: Platinum | J99: 11/19/2023
A100: C2099 | B100: Lakshit Dani | C100: female | D100: -5 | E100: Chenai | F100: Tamil Nadu | G100: fkaul@example.com | H100: +91-9448695946 | I100: None | J100: 15-Aug-2019
...

Sheet Raw_Stores
A1: StoreID | B1: StoreName | C1: City | D1: State | E1: Manager | F1: OpeningDate
A2: S101 | B2: Aurelia Jewels - Surat | C2: Surat | D2: Gujarat | E2: Pratyush Pant | F2: 08-May-2016
A3: S102 | B3: Aurelia Jewels - Chennai | C3: Chennai | D3: Tamil Nadu | E3: Panini Kala | F3: 25-Jun-2016
A4: S103 | B4: Aurelia Jewels - Jaipur | C4: Jaipur | D4: Rajasthan | E4: Nikita Chowdhury | F4: 18/10/2015
A5: S104 | B5: Aurelia Jewels - Ahmedabad | C5: Ahmedabad | D5: Gujarat | E5: Jatin Shukla | F5: 2019-04-19
A6: S105 | B6: Aurelia Jewels - Mumbai | C6: Mumbai | D6: Maharashtra | E6: Zinal Deshpande | F6: 2016-02-24
A7: S106 | B7: Aurelia Jewels - Lucknow | C7: Lucknow | D7: Uttar Pradesh | E7: Jalsa Mani | F7: 07/07/2018
A8: S107 | B8: Aurelia Jewels - Hyderabad | C8: Hyderabad | D8: Telangana | E8: Fitan Narang | F8: 10/05/2018
A9: S108 | B9: Aurelia Jewels - Bengaluru | C9: Bengaluru | D9: Karnataka | E9: Jack Rajan | F9: 17/04/2019

Sheet DataQuality_Log
A1: Data Cleaning Log — Issues Identified & Resolved
A3: Source Sheet | B3: Issue Identified & Action Taken | C3: Rows Affected
A4: Raw_Products | B4: Duplicate ProductID rows removed | C4: 2
A5: Raw_Products | B5: Missing Category filled with mode | C5: 2
A6: Raw_Products | B6: Missing Weight_g filled with median | C6: 1
A7: Raw_Products | B7: Negative StockQty corrected to 0 | C7: 2
A8: Raw_Customers | B8: Rows dropped: blank CustomerID | C8: 1
A9: Raw_Customers | B9: Duplicate CustomerID rows removed | C9: 1
A10: Raw_Customers | B10: Invalid/missing Age filled with median | C10: 123
A11: Raw_Customers | B11: Missing Email flagged as not_provided | C11: 12
A12: Raw_Sales | B12: Exact duplicate transaction rows removed | C12: 4
A13: Raw_Sales | B13: Rows dropped: Quantity <= 0 (data entry errors) | C13: 237
A14: Raw_Sales | B14: Missing CustomerID set to UNKNOWN | C14: 27
A15: Raw_Sales | B15: Rows dropped: ProductID not found in Products master | C15: 0
A17: Total raw sales records: | B17: 954
A18: Clean, analysis-ready sales records: | B18: =COUNTA(Cleaned_Sales!A2:A714) -> 713
A19: Data retained after cleaning: | B19: =B18/B17 -> 0.74737945

Sheet Cleaned_Sales
A1: TransactionID | B1: OrderDate | C1: OrderMonth | D1: OrderYear | E1: CustomerID | F1: ProductID | G1: StoreID | H1: Quantity | I1: UnitPrice | J1: DiscountPct | K1: Revenue | L1: PaymentMode | M1: SalesChannel | N1: SalesRep | O1: Category | P1: Material
A2: TXN5488 | B2: 45048 | C2: 2023-05 | D2: 2023 | E2: C2102 | F2: P1032 | G2: S105 | H2: 1 | I2: 164590 | J2: 0 | K2: 164590 | L2: Cash | M2: In-Store | N2: Indali Kala | O2: =IFERROR(INDEX(Cleaned_Products!$C$2:$C$61,MATCH(F2,Cleaned_Products!$A$2:$A$61,0)),"Unknown") -> Anklets | P2: =IFERROR(INDEX(Cleaned_Products!$D$2:$D$61,MATCH(F2,Cleaned_Products!$A$2:$A$61,0)),"Unknown") -> Gold
A3: TXN5125 | B3: 45623 | C3: 2024-11 | D3: 2024 | E3: C2053 | F3: P1027 | G3: S108 | H3: 1 | I3: 95070 | J3: 15 | K3: 80809.5 | L3: UPI | M3: In-Store | N3: Wriddhish Kulkarni | O3: =IFERROR(INDEX(Cleaned_Products!$C$2:$C$61,MATCH(F3,Cleaned_Products!$A$2:$A$61,0)),"Unknown") -> Anklets | P3: =IFERROR(INDEX(Cleaned_Products!$D$2:$D$61,MATCH(F3,Cleaned_Products!$A$2:$A$61,0)),"Unknown") -> Diamond
A4: TXN5198 | B4: 45258 | C4: 2023-11 | D4: 2023 | E4: C2042 | F4: P1046 | G4: S102 | H4: 1 | I4: 32080 | J4: 10 | K4: 28872 | L4: Credit Card | M4: Online | N4: Harinakshi Sidhu | O4: =IFERROR(INDEX(Cleaned_Products!$C$2:$C$61,MATCH(F4,Cleaned_Products!$A$2:$A$61,0)),"Unknown") -> Rings | P4: =IFERROR(INDEX(Cleaned_Products!$D$2:$D$61,MATCH(F4,Cleaned_Products!$A$2:$A$61,0)),"Unknown") -> Rose Gold
A5: TXN5496 | B5: 45592 | C5: 2024-10 | D5: 2024 | E5: C2103 | F5: P1030 | G5: S102 | H5: 2 | I5: 170430 | J5: 5 | K5: 323817 | L5: Net Banking | M5: Online | N5: Anjali Korpal | O5: =IFERROR(INDEX(Cleaned_Products!$C$2:$C$61,MATCH(F5,Cleaned_Products!$A$2:$A$61,0)),"Unknown") -> Nose Pins | P5: =IFERROR(INDEX(Cleaned_Products!$D$2:$D$61,MATCH(F5,Cleaned_Products!$A$2:$A$61,0)),"Unknown") -> Rose Gold
A6: TXN5395 | B6: 45012 | C6: 2023-03 | D6: 2023 | E6: C2130 | F6: P1014 | G6: S103 | H6: 3 | I6: 136950 | J6: 10 | K6: 369765 | L6: Net Banking | M6: In-Store | N6: Finn Chanda | O6: =IFERROR(INDEX(Cleaned_Products!$C$2:$C$61,MATCH(F6,Cleaned_Products!$A$2:$A$61,0)),"Unknown") -> Nose Pins | P6: =IFERROR(INDEX(Cleaned_Products!$D$2:$D$61,MATCH(F6,Cleaned_Products!$A$2:$A$61,0)),"Unknown") -> Diamond
A7: TXN5719 | B7: 45257 | C7: 2023-11 | D7: 2023 | E7: C2027 | F7: P1041 | G7: S106 | H7: 1 | I7: 43050 | J7: 10 | K7: 38745 | L7: EMI | M7: Online | N7: N/A (Online) | O7: =IFERROR(INDEX(Cleaned_Products!$C$2:$C$61,MATCH(F7,Cleaned_Products!$A$2:$A$61,0)),"Unknown") -> Earrings | P7: =IFERROR(INDEX(Cleaned_Products!$D$2:$D$61,MATCH(F7,Cleaned_Products!$A$2:$A$61,0)),"Unknown") -> Platinum
A8: TXN5273 | B8: 45454 | C8: 2024-06 | D8: 2024 | E8: C2094 | F8: P1057 | G8: S101 | H8: 1 | I8: 98210 | J8: 0 | K8: 98210 | L8: UPI | M8: Online | N8: Yahvi Babu | O8: =IFERROR(INDEX(Cleaned_Products!$C$2:$C$61,MATCH(F8,Cleaned_Products!$A$2:$A$61,0)),"Unknown") -> Bangles | P8: =IFERROR(INDEX(Cleaned_Products!$D$2:$D$61,MATCH(F8,Cleaned_Products!$A$2:$A$61,0)),"Unknown") -> Rose Gold
A9: TXN5602 | B9: 45368 | C9: 2024-03 | D9: 2024 | E9: C2086 | F9: P1004 | G9: S108 | H9: 2 | I9: 94970 | J9: 0 | K9: 189940 | L9: EMI | M9: Online | N9: N/A (Online) | O9: =IFERROR(INDEX(Cleaned_Products!$C$2:$C$61,MATCH(F9,Cleaned_Products!$A$2:$A$61,0)),"Unknown") -> Necklaces | P9: =IFERROR(INDEX(Cleaned_Products!$D$2:$D$61,MATCH(F9,Cleaned_Products!$A$2:$A$61,0)),"Unknown") -> Silver
A10: TXN5073 | B10: 45630 | C10: 2024-12 | D10: 2024 | E10: C2068 | F10: P1030 | G10: S101 | H10: 1 | I10: 204040 | J10: 15 | K10: 173434 | L10: UPI | M10: In-Store | N10: Prisha Kadakia | O10: =IFERROR(INDEX(Cleaned_Products!$C$2:$C$61,MATCH(F10,Cleaned_Products!$A$2:$A$61,0)),"Unknown") -> Nose Pins | P10: =IFERROR(INDEX(Cleaned_Products!$D$2:$D$61,MATCH(F10,Cleaned_Products!$A$2:$A$61,0)),"Unknown") -> Rose Gold
A11: TXN5842 | B11: 44931 | C11: 2023-01 | D11: 2023 | E11: C2085 | F11: P1012 | G11: S107 | H11: 2 | I11: 95460 | J11: 0 | K11: 190920 | L11: Debit Card | M11: Online | N11: Gavin Ghose | O11: =IFERROR(INDEX(Cleaned_Products!$C$2:$C$61,MATCH(F11,Cleaned_Products!$A$2:$A$61,0)),"Unknown") -> Necklaces | P11: =IFERROR(INDEX(Cleaned_Products!$D$2:$D$61,MATCH(F11,Cleaned_Products!$A$2:$A$61,0)),"Unknown") -> Gold
A12: TXN5639 | B12: 45132 | C12: 2023-07 | D12: 2023 | E12: C2016 | F12: P1009 | G12: S104 | H12: 3 | I12: 231350 | J12: 0 | K12: 694050 | L12: Debit Card | M12: Online | N12: N/A (Online) | O12: =IFERROR(INDEX(Cleaned_Products!$C$2:$C$61,MATCH(F12,Cleaned_Products!$A$2:$A$61,0)),"Unknown") -> Rings | P12: =IFERROR(INDEX(Cleaned_Products!$D$2:$D$61,MATCH(F12,Cleaned_Products!$A$2:$A$61,0)),"Unknown") -> Silver
A13: TXN5190 | B13: 45472 | C13: 2024-06 | D13: 2024 | E13: C2031 | F13: P1012 | G13: S106 | H13: 1 | I13: 182860 | J13: 0 | K13: 182860 | L13: Cash | M13: In-Store | N13: Irya Bath | O13: =IFERROR(INDEX(Cleaned_Products!$C$2:$C$61,MATCH(F13,Cleaned_Products!$A$2:$A$61,0)),"Unknown") -> Necklaces | P13: =IFERROR(INDEX(Cleaned_Products!$D$2:$D$61,MATCH(F13,Cleaned_Products!$A$2:$A$61,0)),"Unknown") -> Gold
... A714: TXN5690 | B714: 45435 | C714: 2024-05 | D714: 2024 | E714: C2101 | F714: P1006 | G714: S106 | H714: 1 | I714: 115260 | J714: 0 | K714: 115260 | L714: Cash | M714: In-Store | N714: Urmi Vala | O714: =IFERROR(INDEX(Cleaned_Products!$C$2:$C$61,MATCH(F714,Cleaned_Products!$A$2:$A$61,0)),"Unknown") -> Earrings | P714: =IFERROR(INDEX(Cleaned_Products!$D$2:$D$61,MATCH(F714,Cleaned_Products!$A$2:$A$61,0)),"Unknown") -> Diamond

Sheet Cleaned_Products
A1: ProductID | B1: ProductName | C1: Category | D1: Material | E1: Purity | F1: Weight_g | G1: CostPrice | H1: SellingPrice | I1: Margin | J1: MarginPct | K1: StockQty | L1: StockQty_Flag | M1: Supplier | N1: LaunchDate
A2: P1001 | B2: Gold Ring #1 | C2: Rings | D2: Gold | E2: 24K | F2: 13.46 | G2: 55220 | H2: 79770 | I2: 24550 | J2: 30.78 | K2: 84 | L2: OK | M2: Silver Line Exports | N2: 45293
A3: P1002 | B3: Rose Gold Anklet #2 | C3: Anklets | D3: Rose Gold | E3: 18K | F3: 21.04 | G3: 89440 | H3: 133960 | I3: 44520 | J3: 33.23 | K3: 95 | L3: OK | M3: Diamond Hub Inc | N3: 43792
A4: P1003 | B4: Platinum Bangle #3 | C4: Bangles | D4: Platinum | E4: 950 Platinum | F4: 33.24 | G4: 164470 | H4: 253160 | I4: 88690 | J4: 35.03 | K4: 46 | L4: OK | M4: Rajesh Jewels Pvt Ltd | N4: 44653
A5: P1004 | B5: Silver Necklace #4 | C5: Necklaces | D5: Silver | E5: 999 Silver | F5: 13.59 | G5: 70890 | H5: 91870 | I5: 20980 | J5: 22.84 | K5: 45 | L5: OK | M5: Sundari Gems | N5: 43895
A6: P1005 | B6: Rose Gold Bracelet #5 | C6: Bracelets | D6: Rose Gold | E6: 22K | F6: 38.16 | G6: 213510 | H6: 265100 | I6: 51590 | J6: 19.46 | K6: 2 | L6: OK | M6: Diamond Hub Inc | N6: 44112
A7: P1006 | B7: Diamond Earring #6 | C7: Earrings | D7: Diamond | E7: Platinum + Diamond | F7: 7.57 | G7: 41720 | H7: 56970 | I7: 15250 | J7: 26.77 | K7: 93 | L7: OK | M7: Kundan Creations | N7: 44343
A8: P1007 | B8: Silver Anklet #7 | C8: Anklets | D8: Silver | E8: 925 Silver | F8: 18.24 | G8: 93190 | H8: 124620 | I8: 31430 | J8: 25.22 | K8: 30 | L8: OK | M8: Kundan Creations | N8: 45228
A9: P1008 | B9: Platinum Earring #8 | C9: Earrings | D9: Platinum | E9: 950 Platinum | F9: 39.37 | G9: 169520 | H9: 238270 | I9: 68750 | J9: 28.85 | K9: 75 | L9: OK | M9: GoldCraft Traders | N9: 43749
A10: P1009 | B10: Silver Ring #9 | C10: Rings | D10: Silver | E10: 925 Silver | F10: 39.69 | G10: 240390 | H10: 284680 | I10: 44290 | J10: 15.56 | K10: 60 | L10: OK | M10: Diamond Hub Inc | N10: 43607
A11: P1010 | B11: Rose Gold Bracelet #10 | C11: Bracelets | D11: Rose Gold | E11: 22K | F11: 18.86 | G11: 100210 | H11: 130210 | I11: 30000 | J11: 23.04 | K11: 113 | L11: OK | M11: Kundan Creations | N11: 44390
A12: P1011 | B12: Gold Bracelet #11 | C12: Bracelets | D12: Gold | E12: 18K | F12: 40.89 | G12: 238020 | H12: 280470 | I12: 42450 | J12: 15.14 | K12: 28 | L12: OK | M12: Sundari Gems | N12: 44836
A13: P1012 | B13: Gold Necklace #12 | C13: Necklaces | D13: Gold | E13: 24K | F13: 20.25 | G13: 94030 | H13: 125700 | I13: 31670 | J13: 25.19 | K13: 91 | L13: OK | M13: Rajesh Jewels Pvt Ltd | N13: 44845
A14: P1013 | B14: Diamond Earring #13 | C14: Earrings | E14: Platinum + Diamond | F14: 21.62 | G14: 126720 | H14: 149550 | I14: 22830 | J14: 15.27 | K14: 101 | L14: OK | M14: Diamond Hub Inc | N14: 45219
A15: P1014 | B15: Diamond Nose Pin #14 | C15: Nose Pins | D15: Diamond | E15: Platinum + Diamond | F15: 10.8 | G15: 49490 | H15: 58070 | I15: 8580 | J15: 14.78 | K15: 46 | L15: OK | M15: Rajesh Jewels Pvt Ltd | N15: 44472
A16: P1015 | B16: Platinum Bracelet #15 | C16: Bracelets | D16: Platinum | E16: 950 Platinum | F16: 26.69 | G16: 132490 | H16: 192000 | I16: 59510 | J16: 30.99 | K16: 5 | L16: OK | M16: Rajesh Jewels Pvt Ltd | N16: 44662
A17: P1016 | B17: Diamond Necklace #16 | C17: Necklaces | D17: Diamond | E17: 18K Gold + Diamond | F17: 26.68 | G17: 96240 | H17: 113830 | I17: 17590 | J17: 15.45 | K17: 82 | L17: OK | M17: Kundan Creations | N17: 44623
A18: P1017 | B18: Platinum Necklace #17 | C18: Necklaces | D18: Platinum | E18: 950 Platinum | F18: 21.44 | G18: 132840 | H18: 205690 | I18: 72850 | J18: 35.42 | K18: 7 | L18: OK | M18: Kundan Creations | N18: 43902
A19: P1018 | B19: Platinum Ring #18 | C19: Rings | D19: Platinum | E19: 950 Platinum | F19: 42.03 | G19: 158860 | H19: 238490 | I19: 79630 | J19: 33.39 | K19: 31 | L19: OK | M19: Rajesh Jewels Pvt Ltd | N19: 45288
A20: P1019 | B20: Diamond Bangle #19 | C20: Bangles | D20: Diamond | E20: 18K Gold + Diamond | F20: 26.57 | G20: 25590 | H20: 32260 | I20: 6670 | J20: 20.68 | K20: 0 | L20: ERROR: Negative Stock Corrected | M20: Sundari Gems | N20: 45045
A21: P1020 | B21: Silver Ring #20 | C21: Rings | D21: Silver | E21: 999 Silver | F21: 26.84 | G21: 104670 | H21: 125710 | I21: 21040 | J21: 16.74 | K21: 37 | L21: OK | M21: Sundari Gems | N21: 45307
A22: P1021 | B22: Silver Bracelet #21 | C22: Bracelets | D22: Silver | E22: 925 Silver | F22: 43.96 | G22: 250090 | H22: 375780 | I22: 125690 | J22: 33.45 | K22: 1 | L22: OK | M22: GoldCraft Traders | N22: 44974
A23: P1022 | B23: Diamond Pendant #22 | C23: Pendants | D23: Diamond | E23: Platinum + Diamond | F23: 37.19 | G23: 217660 | H23: 269720 | I23: 52060 | J23: 19.3 | K23: 82 | L23: OK | M23: GoldCraft Traders | N23: 44282
A24: P1023 | B24: Gold Necklace #23 | C24: Necklaces | D24: Gold | E24: 22K | F24: 9.27 | G24: 56540 | H24: 71020 | I24: 14480 | J24: 20.39 | K24: 11 | L24: OK | M24: Kundan Creations | N24: 44414
A25: P1024 | B25: Gold Bracelet #24 | C25: Bracelets | D25: Gold | E25: 22K | F25: 20.26 | G25: 122820 | H25: 186480 | I25: 63660 | J25: 34.14 | K25: 77 | L25: OK | M25: Sundari Gems | N25: 44824
A26: P1025 | B26: Diamond Earring #25 | C26: Earrings | D26: Diamond | E26: Platinum + Diamond | F26: 19.16 | G26: 110190 | H26: 140110 | I26: 29920 | J26: 21.35 | K26: 24 | L26: OK | M26: Malabar Suppliers | N26: 45075
... A61: P1060 | B61: Diamond Pendant #60 | C61: Pendants | D61: Diamond | E61: 18K Gold + Diamond | F61: 35.89 | G61: 126960 | H61: 173250 | I61: 46290 | J61: 26.72 | K61: 56 | L61: OK | M61: Sundari Gems | N61: 44843

Sheet Cleaned_Customers
A1: CustomerID | B1: CustomerName | C1: Gender | D1: Age | E1: City | F1: State | G1: Email | H1: Phone | I1: MembershipTier | J1: JoinDate
A2: C2001 | B2: Kritika Brar | C2: Female | D2: 44 | E2: Chennai | F2: Tamil Nadu | G2: bakshianvi@example.org | H2: 1960013389 | I2: Silver | J2: 45002
A3: C2002 | B3: Alka Dewan | C3: Female | D3: 43 | E3: Delhi | F3: Delhi | G3: janaki93@example.net | H3: 2832764835 | I3: Gold | J3: 45302
A4: C2003 | B4: Neel Zacharia | C4: Male | D4: 43 | E4: Surat | F4: Gujarat | G4: adyasangha@example.net | H4: 8480184514 | I4: Platinum | J4: 44246
A5: C2004 | B5: Veer Bir | C5: Male | D5: 43 | E5: Jaipur | F5: Rajasthan | G5: naikvrinda@example.org | H5: 8963834657 | I5: Silver | J5: 43349
A6: C2005 | B6: Girik Khalsa | C6: Male | D6: 43 | E6: Hyderabad | F6: Telangana | G6: narayananekavir@example.net | H6: 6701065133 | I6: Silver | J6: 43616
A7: C2006 | B7: Finn Saini | C7: Male | D7: 43 | E7: Mumbai | F7: Maharashtra | G7: niharikasunder@example.com | H7: 6064746872 | I7: Gold | J7: 43693
A8: C2007 | B8: Samar Lalla | C8: Female | D8: 43 | E8: Surat | F8: Gujarat | G8: advika35@example.org | H8: 7510799118 | I8: Silver | J8: 43165
A9: C2008 | B9: Gaurangi Sabharwal | C9: Female | D9: 57 | E9: Surat | F9: Gujarat | G9: dkrishnamurthy@example.org | H9: 5869232260 | I9: Silver | J9: 44952
A10: C2009 | B10: Chaitanya Sarin | C10: Male | D10: 43 | E10: Ahmedabad | F10: Gujarat | G10: not_provided@unknown.com | H10: 3375433036 | I10: Silver | J10: 44847
A11: C2010 | B11: Girik Keer | C11: Male | D11: 43 | E11: Bengaluru | F11: Karnataka | G11: venkateshronith@example.com | H11: 7773872148 | I11: Gold | J11: 45658
A12: C2011 | B12: William Maharaj | C12: Female | D12: 43 | E12: Lucknow | F12: Uttar Pradesh | G12: umang32@example.org | H12: Not Provided | J12: 45359
A13: C2012 | B13: Lopa Nayar | C13: Female | D13: 43 | E13: Pune | F13: Maharashtra | G13: tbrahmbhatt@example.com | H13: Not Provided | I13: Silver | J13: 44381
A14: C2013 | B14: Udyati Kunda | C14: Male | D14: 43 | E14: Pune | F14: Maharashtra | G14: dgandhi@example.org | H14: Not Provided | I14: Gold | J14: 44627
A15: C2014 | B15: Rajata Loyal | C15: Female | D15: 43 | E15: Kolkata | F15: West Bengal | G15: oliver99@example.net | H15: 9058651850 | I15: Gold | J15: 44541
A16: C2015 | B16: Pavani Narayanan | C16: Female | D16: 45 | E16: Hyderabad | F16: Telangana | G16: yatan14@example.com | H16: 1436349578 | I16: Silver | J16: 44242
A17: C2016 | B17: Ishaan Bhattacharyya | C17: Female | D17: 43 | E17: Hyderabad | F17: Telangana | G17: not_provided@unknown.com | H17: 1823374989 | J17: 43126
A18: C2017 | B18: Vincent Mani | C18: Male | D18: 43 | E18: Pune | F18: Maharashtra | G18: eswamy@example.net | H18: 4131869993 | I18: Gold | J18: 44497
A19: C2018 | B19: Zilmil Sathe | C19: Male | D19: 43 | E19: Surat | F19: Gujarat | G19: sudiksha13@example.com | H19: Not Provided | I19: Gold | J19: 43112
A20: C2019 | B20: Ayush Khatri | C20: Male | D20: 43 | E20: Pune | F20: Maharashtra | G20: not_provided@unknown.com | H20: Not Provided | I20: Platinum | J20: 44261
A21: C2020 | B21: Tamanna Nagy | C21: Male | D21: 43 | E21: Chennai | F21: Tamil Nadu | G21: deepaatwal@example.net | H21: Not Provided | J21: 43966
A22: C2021 | B22: Guneet Chaudhry | C22: Male | D22: 43 | E22: Pune | F22: Maharashtra | G22: not_provided@unknown.com | H22: 6627028951 | J22: 45150
A23: C2022 | B23: Rushil Rajagopalan | C23: Female | D23: 43 | E23: Hyderabad | F23: Telangana | G23: sganesan@example.com | H23: 4556238692 | I23: Platinum | J23: 45449
A24: C2023 | B24: Chakrika Nigam | C24: Male | D24: 43 | E24: Ahmedabad | F24: Gujarat | G24: pchhabra@example.com | H24: 0640909743 | J24: 43461
A25: C2024 | B25: Oni Dubey | C25: Female | D25: 43 | E25: Chennai | F25: Tamil Nadu | G25: sidhufaqid@example.org | H25: 0471138267 | I25: Gold | J25: 43789
A26: C2025 | B26: Owen Choudhary | C26: Male | D26: 27 | E26: Delhi | F26: Delhi | G26: fchaudhary@example.net | H26: Not Provided | I26: Silver | J26: 44149
A27: C2026 | B27: Lakshmi Wali | C27: Female | D27: 43 | E27: Coimbatore | F27: Tamil Nadu | G27: deepalexander@example.com | H27: 7711592124 | I27: Gold | J27: 44395
A28: C2027 | B28: Yashica Kala | C28: Female | D28: 43 | E28: Delhi | F28: Delhi | G28: not_provided@unknown.com | H28: 6736576615 | I28: Silver | J28: 44992
A29: C2028 | B29: Charles Dugal | C29: Female | D29: 43 | E29: Surat | F29: Gujarat | G29: vasatikakapur@example.org | H29: 4936899809 | I29: Platinum | J29: 44943
A30: C2029 | B30: Mekhala Basak | C30: Female | D30: 43 | E30: Jaipur | F30: Rajasthan | G30: chandranbumb@example.com | H30: 7622683885 | I30: Platinum | J30: 43261
A31: C2030 | B31: Rudra Ghose | C31: Female | D31: 43 | E31: Mumbai | F31: Maharashtra | G31: dbahl@example.org | H31: 3696816453 | I31: Silver | J31: 43370
A32: C2031 | B32: Yachana Dora | C32: Male | D32: 43 | E32: Kolkata | F32: West Bengal | G32: faqidgoel@example.net | H32: 8679807935 | I32: Platinum | J32: 43629
A33: C2032 | B33: Joshua Vyas | C33: Male | D33: 43 | E33: Jaipur | F33: Rajasthan | G33: seshadriharshil@example.com | H33: Not Provided | I33: Silver | J33: 43175
A34: C2033 | B34: Triya Manda | C34: Male | D34: 65 | E34: Delhi | F34: Delhi | G34: sampathyashoda@example.com | H34: 9622292706 | J34: 43515
A35: C2034 | B35: Liam Singh | C35: Male | D35: 43 | E35: Bengaluru | F35: Karnataka | G35: hthakkar@example.com | H35: 5305152204 | I35: Gold | J35: 44893
A36: C2035 | B36: Madhavi Singhal | C36: Female | D36: 43 | E36: Jaipur | F36: Rajasthan | G36: fahluwalia@example.org | H36: Not Provided | J36: 44368
A37: C2036 | B37: Ria Raju | C37: Female | D37: 43 | E37: Jaipur | F37: Rajasthan | G37: not_provided@unknown.com | H37: Not Provided | J37: 43764
A38: C2037 | B38: Leela Bali | C38: Male | D38: 43 | E38: Delhi | F38: Delhi | G38: rachit77@example.com | H38: 6928451154 | I38: Silver | J38: 43444
A39: C2038 | B39: Jairaj Iyer | C39: Male | D39: 43 | E39: Hyderabad | F39: Telangana | G39: shivaniprabhakar@example.com | H39: 8565431027 | I39: Gold | J39: 44800
A40: C2039 | B40: Farhan Krishna | C40: Male | D40: 43 | E40: Delhi | F40: Delhi | G40: warjastak@example.org | H40: Not Provided | I40: Silver | J40: 43699
A41: C2040 | B41: Maanas Munshi | C41: Male | D41: 43 | E41: Mumbai | F41: Maharashtra | G41: anvidass@example.net | H41: 4710276773 | I41: Gold | J41: 43984
A42: C2041 | B42: Bhavika Yadav | C42: Male | D42: 49 | E42: Chennai | F42: Tamil Nadu | G42: hemani62@example.com | H42: 9532787747 | I42: Silver | J42: 45652
A43: C2042 | B43: Manthan Varma | C43: Female | D43: 29 | E43: Mumbai | F43: Maharashtra | G43: chokshiraagini@example.org | H43: 8680002578 | I43: Gold | J43: 44546
A44: C2043 | B44: Max Sachar | C44: Male | D44: 43 | E44: Ahmedabad | F44: Gujarat | G44: falaknagar@example.org | H44: 6230913075 | I44: Silver | J44: 44656
A45: C2044 | B45: Bina Basak | C45: Male | D45: 43 | E45: Lucknow | F45: Uttar Pradesh | G45: nirjathaker@example.net | H45: Not Provided | I45: Gold | J45: 43647
A46: C2045 | B46: Patrick Bansal | C46: Female | D46: 43 | E46: Bengaluru | F46: Karnataka | G46: farhan57@example.net | H46: 4540193802 | I46: Silver | J46: 44975
A47: C2046 | B47: Advika Rajagopal | C47: Female | D47: 40 | E47: Ahmedabad | F47: Gujarat | G47: ltandon@example.net | H47: 8516122753 | I47: Silver | J47: 43250
A48: C2047 | B48: Mason Gala | C48: Female | D48: 43 | E48: Pune | F48: Maharashtra | G48: sanyaloke@example.com | H48: 9187851910 | J48: 44625
A49: C2048 | B49: Kiaan Pall | C49: Female | D49: 43 | E49: Pune | F49: Maharashtra | G49: zinal71@example.net | H49: 4622656766 | I49: Silver | J49: 45335
A50: C2049 | B50: Eiravati Nagi | C50: Female | D50: 43 | E50: Lucknow | F50: Uttar Pradesh | G50: gokhalemaya@example.net | H50: 4786863375 | I50: Silver | J50: 44540
A51: C2050 | B51: George Wason | C51: Female | D51: 43 | E51: Jaipur | F51: Rajasthan | G51: not_provided@unknown.com | H51: 0892687056 | J51: 43228
A52: C2051 | B52: Madhav Babu | C52: Female | D52: 43 | E52: Pune | F52: Maharashtra | G52: charanloyal@example.com | H52: 8373540331 | I52: Platinum | J52: 45579
A53: C2052 | B53: Nisha Arora | C53: Female | D53: 43 | E53: Hyderabad | F53: Telangana | G53: omisha42@example.org | H53: 3785477725 | I53: Silver | J53: 44123
A54: C2053 | B54: Victor Kakar | C54: Female | D54: 43 | E54: Chennai | F54: Tamil Nadu | G54: wagleanvi@example.net | H54: Not Provided | I54: Silver | J54: 45112
A55: C2054 | B55: Rachana Grewal | C55: Female | D55: 43 | E55: Lucknow | F55: Uttar Pradesh | G55: cmadan@example.org | H55: 5621850163 | I55: Silver | J55: 45353
A56: C2055 | B56: Xavier Verma | C56: Male | D56: 43 | E56: Chennai | F56: Tamil Nadu | G56: xchada@example.net | H56: 1212678886 | I56: Silver | J56: 44070
A57: C2056 | B57: Eiravati Manne | C57: Male | D57: 44 | E57: Kolkata | F57: West Bengal | G57: lajitagara@example.org | H57: 6924593752 | I57: Gold | J57: 45061
A58: C2057 | B58: Ojas Basu | C58: Female | D58: 43 | E58: Coimbatore | F58: Tamil Nadu | G58: ukibe@example.com | H58: 9398280737 | I58: Gold | J58: 43626
A59: C2058 | B59: Ishwar Bajaj | C59: Male | D59: 43 | E59: Bengaluru | F59: Karnataka | G59: ynarula@example.com | H59: 8757177514 | I59: Silver | J59: 44422
A60: C2059 | B60: Ijaya Pandey | C60: Female | D60: 43 | E60: Coimbatore | F60: Tamil Nadu | G60: ikbal23@example.net | H60: 6033419182 | I60: Silver | J60: 45617
A61: C2060 | B61: Nilima Swamy | C61: Female | D61: 43 | E61: Mumbai | F61: Maharashtra | G61: rgera@example.net | H61: Not Provided | J61: 43433
A62: C2061 | B62: Liam Jhaveri | C62: Male | D62: 43 | E62: Coimbatore | F62: Tamil Nadu | G62: fsawhney@example.org | H62: 4043842797 | I62: Silver | J62: 44338
A63: C2062 | B63: Dev Warrior | C63: Male | D63: 43 | E63: Pune | F63: Maharashtra | G63: danielpanchal@example.net | H63: 8457759017 | I63: Silver | J63: 45003
A64: C2063 | B64: Faras Deo | C64: Female | D64: 43 | E64: Bengaluru | F64: Karnataka | G64: bkamdar@example.org | H64: Not Provided | I64: Silver | J64: 45210
A65: C2064 | B65: Yug Malhotra | C65: Male | D65: 43 | E65: Kolkata | F65: West Bengal | G65: zilmilsaxena@example.org | H65: 3112196565 | I65: Silver | J65: 45621
A66: C2065 | B66: Pallavi Ratti | C66: Male | D66: 43 | E66: Jaipur | F66: Rajasthan | G66: kotharibhavani@example.net | H66: 8055269658 | I66: Gold | J66: 45054
A67: C2066 | B67: Anita Viswanathan | C67: Female | D67: 43 | E67: Mumbai | F67: Maharashtra | G67: yadavmichael@example.com | H67: 3285691463 | J67: 45128
A68: C2067 | B68: Nandini Biswas | C68: Female | D68: 43 | E68: Kolkata | F68: West Bengal | G68: lallfaraj@example.com | H68: 4195180238 | I68: Silver | J68: 44841
A69: C2068 | B69: Kashish Shanker | C69: Female | D69: 43 | E69: Kolkata | F69: West Bengal | G69: xmandal@example.com | H69: 8367024103 | I69: Gold | J69: 43628
A70: C2069 | B70: Tanveer Narang | C70: Male | D70: 43 | E70: Jaipur | F70: Rajasthan | G70: chandranyashasvi@example.org | H70: Not Provided | I70: Silver | J70: 45149
A71: C2070 | B71: Megha Taneja | C71: Male | D71: 43 | E71: Surat | F71: Gujarat | G71: gavinkothari@example.com | H71: Not Provided | J71: 43766
A72: C2071 | B72: Ayushman Mand | C72: Female | D72: 43 | E72: Mumbai | F72: Maharashtra | G72: rajapooja@example.org | H72: 4720999347 | I72: Silver | J72: 44457
A73: C2072 | B73: Kalpit Oak | C73: Female | D73: 43 | E73: Surat | F73: Gujarat | G73: sodhiishita@example.net | H73: 9059929378 | I73: Gold | J73: 43311
A74: C2073 | B74: Watika Dhaliwal | C74: Male | D74: 43 | E74: Mumbai | F74: Maharashtra | G74: ekiyabhargava@example.org | H74: Not Provided | I74: Silver | J74: 44385
A75: C2074 | B75: Girik Nigam | C75: Male | D75: 43 | E75: Jaipur | F75: Rajasthan | G75: faras35@example.com | H75: 6765861793 | J75: 45398
A76: C2075 | B76: Vrinda Lanka | C76: Female | D76: 43 | E76: Hyderabad | F76: Telangana | G76: bbalasubramanian@example.net | H76: 6987205061 | I76: Silver | J76: 45599
A77: C2076 | B77: Oliver Kakar | C77: Female | D77: 43 | E77: Lucknow | F77: Uttar Pradesh | G77: ramqasim@example.com | H77: Not Provided | I77: Gold | J77: 45103
A78: C2077 | B78: Orinder Majumdar | C78: Female | D78: 43 | E78: Bengaluru | F78: Karnataka | G78: jonathanbasak@example.com | H78: 4856467997 | J78: 43273
A79: C2078 | B79: Oscar Hans | C79: Male | D79: 43 | E79: Jaipur | F79: Rajasthan | G79: ndhawan@example.net | H79: 4754691373 | I79: Silver | J79: 45403
A80: C2079 | B80: Udarsh Krishnan | C80: Male | D80: 26 | E80: Pune | F80: Maharashtra | G80: dalbirkrish@example.org | H80: 8552414060 | I80: Platinum | J80: 45035
A81: C2080 | B81: Hemal Kapadia | C81: Female | D81: 21 | E81: Coimbatore | F81: Tamil Nadu | G81: anvi66@example.com | H81: 1545444328 | I81: Silver | J81: 44277
A82: C2081 | B82: Tanvi Dhar | C82: Male | D82: 43 | E82: Pune | F82: Maharashtra | G82: gparmer@example.com | H82: 1724825135 | J82: 43249
A83: C2082 | B83: Chakradev Misra | C83: Male | D83: 43 | E83: Kolkata | F83: West Bengal | G83: pranit17@example.com | H83: 7432927129 | I83: Gold | J83: 45326
A84: C2083 | B84: Osha Chaudhuri | C84: Female | D84: 43 | E84: Lucknow | F84: Uttar Pradesh | G84: tamanna89@example.net | H84: Not Provided | I84: Silver | J84: 43158
A85: C2084 | B85: Bina Parsa | C85: Female | D85: 33 | E85: Pune | F85: Maharashtra | G85: laksh61@example.net | H85: 3753001197 | I85: Gold | J85: 43857
A86: C2085 | B86: Chakradhar Bhatnagar | C86: Female | D86: 33 | E86: Kolkata | F86: West Bengal | G86: pooja11@example.org | H86: Not Provided | I86: Gold | J86: 44172
A87: C2086 | B87: Widisha Badami | C87: Female | D87: 43 | E87: Lucknow | F87: Uttar Pradesh | G87: dipta08@example.net | H87: 7721753540 | J87: 43581
A88: C2087 | B88: Tanvi Halder | C88: Female | D88: 43 | E88: Ahmedabad | F88: Gujarat | G88: ravalnitara@example.org | H88: 4883755037 | I88: Gold | J88: 44804
A89: C2088 | B89: Sai Kadakia | C89: Female | D89: 43 | E89: Surat | F89: Gujarat | G89: hritik60@example.net | H89: Not Provided | J89: 43353
A90: C2089 | B90: Omaja Munshi | C90: Male | D90: 43 | E90: Ahmedabad | F90: Gujarat | G90: hemani22@example.net | H90: Not Provided | J90: 45191
A91: C2090 | B91: Qarin Verma | C91: Female | D91: 43 | E91: Lucknow | F91: Uttar Pradesh | G91: aryazayan@example.org | H91: 8933472122 | J91: 44840
A92: C2091 | B92: Oliver Yogi | C92: Male | D92: 43 | E92: Mumbai | F92: Maharashtra | G92: tiwarinathaniel@example.com | H92: Not Provided | I92: Silver | J92: 45034
A93: C2092 | B93: Gabriel Manda | C93: Female | D93: 43 | E93: Pune | F93: Maharashtra | G93: bhattishivansh@example.net | H93: 0919015814 | J93: 43429
A94: C2093 | B94: Elijah Mannan | C94: Female | D94: 43 | E94: Bengaluru | F94: Karnataka | G94: zraj@example.net | H94: 9968814353 | J94: 43115
A95: C2094 | B95: Avni Dey | C95: Female | D95: 44 | E95: Kolkata | F95: West Bengal | G95: krishnaguneet@example.org | H95: 3149135775 | J95: 43563
A96: C2095 | B96: Theodore Sura | C96: Male | D96: 43 | E96: Surat | F96: Gujarat | G96: adyabose@example.net | H96: 9969308488 | I96: Silver | J96: 44103
A97: C2096 | B97: Siddharth Doctor | C97: Female | D97: 43 | E97: Lucknow | F97: Uttar Pradesh | G97: devlalla@example.com | H97: 2665918463 | J97: 45466
A98: C2097 | B98: Qabil Vaidya | C98: Male | D98: 43 | E98: Kolkata | F98: West Bengal | G98: nakulpathak@example.net | H98: Not Provided | J98: 43350
A99: C2098 | B99: Krish Kumar | C99: Male | D99: 43 | E99: Coimbatore | F99: Tamil Nadu | G99: oliver57@example.net | H99: 0881172980 | I99: Platinum | J99: 45249
A100: C2099 | B100: Lakshit Dani | C100: Female | D100: 43 | E100: Chennai | F100: Tamil Nadu | G100: fkaul@example.com | H100: 9448695946 | J100: 43692
...

Sheet Cleaned_Stores
A1: StoreID | B1: StoreName | C1: City | D1: State | E1: Manager | F1: OpeningDate
A2: S101 | B2: Aurelia Jewels - Surat | C2: Surat | D2: Gujarat | E2: Pratyush Pant | F2: 42498
A3: S102 | B3: Aurelia Jewels - Chennai | C3: Chennai | D3: Tamil Nadu | E3: Panini Kala | F3: 42546
A4: S103 | B4: Aurelia Jewels - Jaipur | C4: Jaipur | D4: Rajasthan | E4: Nikita Chowdhury | F4: 42295
A5: S104 | B5: Aurelia Jewels - Ahmedabad | C5: Ahmedabad | D5: Gujarat | E5: Jatin Shukla | F5: 43574
A6: S105 | B6: Aurelia Jewels - Mumbai | C6: Mumbai | D6: Maharashtra | E6: Zinal Deshpande | F6: 42424
A7: S106 | B7: Aurelia Jewels - Lucknow | C7: Lucknow | D7: Uttar Pradesh | E7: Jalsa Mani | F7: 43288
A8: S107 | B8: Aurelia Jewels - Hyderabad | C8: Hyderabad | D8: Telangana | E8: Fitan Narang | F8: 43230
A9: S108 | B9: Aurelia Jewels - Bengaluru | C9: Bengaluru | D9: Karnataka | E9: Jack Rajan | F9: 43572

Sheet Classification
A1: Product & Customer Classification
A3: PRODUCT ABC CLASSIFICATION (Pareto analysis on revenue contribution)
A4: ProductID | B4: ProductName | C4: Category | D4: TotalRevenue | E4: TotalQtySold | F4: RevenueRank | G4: CumulativeRevenue% | H4: ABC Class
A5: =Cleaned_Products!A2 -> P1001 | B5: =Cleaned_Products!B2 -> Gold Ring #1 | C5: =Cleaned_Products!C2 -> Rings | D5: =SUMIF(Cleaned_Sales!$F$2:$F$714,A5,Cleaned_Sales!$K$2:$K$714) -> 3796538 | E5: =SUMIF(Cleaned_Sales!$F$2:$F$714,A5,Cleaned_Sales!$H$2:$H$714) -> 25 | F5: =RANK(D5,$D$5:$D$64) -> 4 | G5: =SUMIF($F$5:$F$64,"<="&F5,$D$5:$D$64)/SUM($D$5:$D$64) -> 0.12488666 | H5: =IF(G5<=0.8,"A - Top Contributor",IF(G5<=0.95,"B - Moderate","C - Low")) -> A - Top Contributor
A6: =Cleaned_Products!A3 -> P1002 | B6: =Cleaned_Products!B3 -> Rose Gold Anklet #2 | C6: =Cleaned_Products!C3 -> Anklets | D6: =SUMIF(Cleaned_Sales!$F$2:$F$714,A6,Cleaned_Sales!$K$2:$K$714) -> 1833501 | E6: =SUMIF(Cleaned_Sales!$F$2:$F$714,A6,Cleaned_Sales!$H$2:$H$714) -> 15 | F6: =RANK(D6,$D$5:$D$64) -> 44 | G6: =SUMIF($F$5:$F$64,"<="&F6,$D$5:$D$64)/SUM($D$5:$D$64) -> 0.85481952 | H6: =IF(G6<=0.8,"A - Top Contributor",IF(G6<=0.95,"B - Moderate","C - Low")) -> B - Moderate
A7: =Cleaned_Products!A4 -> P1003 | B7: =Cleaned_Products!B4 -> Platinum Bangle #3 | C7: =Cleaned_Products!C4 -> Bangles | D7: =SUMIF(Cleaned_Sales!$F$2:$F$714,A7,Cleaned_Sales!$K$2:$K$714) -> 2454108 | E7: =SUMIF(Cleaned_Sales!$F$2:$F$714,A7,Cleaned_Sales!$H$2:$H$714) -> 22 | F7: =RANK(D7,$D$5:$D$64) -> 26 | G7: =SUMIF($F$5:$F$64,"<="&F7,$D$5:$D$64)/SUM($D$5:$D$64) -> 0.58156358 | H7: =IF(G7<=0.8,"A - Top Contributor",IF(G7<=0.95,"B - Moderate","C - Low")) -> A - Top Contributor
A8: =Cleaned_Products!A5 -> P1004 | B8: =Cleaned_Products!B5 -> Silver Necklace #4 | C8: =Cleaned_Products!C5 -> Necklaces | D8: =SUMIF(Cleaned_Sales!$F$2:$F$714,A8,Cleaned_Sales!$K$2:$K$714) -> 2011623 | E8: =SUMIF(Cleaned_Sales!$F$2:$F$714,A8,Cleaned_Sales!$H$2:$H$714) -> 19 | F8: =RANK(D8,$D$5:$D$64) -> 42 | G8: =SUMIF($F$5:$F$64,"<="&F8,$D$5:$D$64)/SUM($D$5:$D$64) -> 0.82833295 | H8: =IF(G8<=0.8,"A - Top Contributor",IF(G8<=0.95,"B - Moderate","C - Low")) -> B - Moderate
A9: =Cleaned_Products!A6 -> P1005 | B9: =Cleaned_Products!B6 -> Rose Gold Bracelet #5 | C9: =Cleaned_Products!C6 -> Bracelets | D9: =SUMIF(Cleaned_Sales!$F$2:$F$714,A9,Cleaned_Sales!$K$2:$K$714) -> 1613618 | E9: =SUMIF(Cleaned_Sales!$F$2:$F$714,A9,Cleaned_Sales!$H$2:$H$714) -> 15 | F9: =RANK(D9,$D$5:$D$64) -> 49 | G9: =SUMIF($F$5:$F$64,"<="&F9,$D$5:$D$64)/SUM($D$5:$D$64) -> 0.91476083 | H9: =IF(G9<=0.8,"A - Top Contributor",IF(G9<=0.95,"B - Moderate","C - Low")) -> B - Moderate
A10: =Cleaned_Products!A7 -> P1006 | B10: =Cleaned_Products!B7 -> Diamond Earring #6 | C10: =Cleaned_Products!C7 -> Earrings | D10: =SUMIF(Cleaned_Sales!$F$2:$F$714,A10,Cleaned_Sales!$K$2:$K$714) -> 5735571.5 | E10: =SUMIF(Cleaned_Sales!$F$2:$F$714,A10,Cleaned_Sales!$H$2:$H$714) -> 48 | F10: =RANK(D10,$D$5:$D$64) -> 1 | G10: =SUMIF($F$5:$F$64,"<="&F10,$D$5:$D$64)/SUM($D$5:$D$64) -> 0.041028747 | H10: =IF(G10<=0.8,"A - Top Contributor",IF(G10<=0.95,"B - Moderate","C - Low")) -> A - Top Contributor
A11: =Cleaned_Products!A8 -> P1007 | B11: =Cleaned_Products!B8 -> Silver Anklet #7 | C11: =Cleaned_Products!C8 -> Anklets | D11: =SUMIF(Cleaned_Sales!$F$2:$F$714,A11,Cleaned_Sales!$K$2:$K$714) -> 2028667 | E11: =SUMIF(Cleaned_Sales!$F$2:$F$714,A11,Cleaned_Sales!$H$2:$H$714) -> 22 | F11: =RANK(D11,$D$5:$D$64) -> 39 | G11: =SUMIF($F$5:$F$64,"<="&F11,$D$5:$D$64)/SUM($D$5:$D$64) -> 0.7850827 | H11: =IF(G11<=0.8,"A - Top Contributor",IF(G11<=0.95,"B - Moderate","C - Low")) -> A - Top Contributor
A12: =Cleaned_Products!A9 -> P1008 | B12: =Cleaned_Products!B9 -> Platinum Earring #8 | C12: =Cleaned_Products!C9 -> Earrings | D12: =SUMIF(Cleaned_Sales!$F$2:$F$714,A12,Cleaned_Sales!$K$2:$K$714) -> 2097610 | E12: =SUMIF(Cleaned_Sales!$F$2:$F$714,A12,Cleaned_Sales!$H$2:$H$714) -> 19 | F12: =RANK(D12,$D$5:$D$64) -> 33 | G12: =SUMIF($F$5:$F$64,"<="&F12,$D$5:$D$64)/SUM($D$5:$D$64) -> 0.69668236 | H12: =IF(G12<=0.8,"A - Top Contributor",IF(G12<=0.95,"B - Moderate","C - Low")) -> A - Top Contributor
A13: =Cleaned_Products!A10 -> P1009 | B13: =Cleaned_Products!B10 -> Silver Ring #9 | C13: =Cleaned_Products!C10 -> Rings | D13: =SUMIF(Cleaned_Sales!$F$2:$F$714,A13,Cleaned_Sales!$K$2:$K$714) -> 3069356 | E13: =SUMIF(Cleaned_Sales!$F$2:$F$714,A13,Cleaned_Sales!$H$2:$H$714) -> 23 | F13: =RANK(D13,$D$5:$D$64) -> 12 | G13: =SUMIF($F$5:$F$64,"<="&F13,$D$5:$D$64)/SUM($D$5:$D$64) -> 0.31876499 | H13: =IF(G13<=0.8,"A - Top Contributor",IF(G13<=0.95,"B - Moderate","C - Low")) -> A - Top Contributor
A14: =Cleaned_Products!A11 -> P1010 | B14: =Cleaned_Products!B11 -> Rose Gold Bracelet #10 | C14: =Cleaned_Products!C11 -> Bracelets | D14: =SUMIF(Cleaned_Sales!$F$2:$F$714,A14,Cleaned_Sales!$K$2:$K$714) -> 4017876.5 | E14: =SUMIF(Cleaned_Sales!$F$2:$F$714,A14,Cleaned_Sales!$H$2:$H$714) -> 30 | F14: =RANK(D14,$D$5:$D$64) -> 2 | G14: =SUMIF($F$5:$F$64,"<="&F14,$D$5:$D$64)/SUM($D$5:$D$64) -> 0.069770162 | H14: =IF(G14<=0.8,"A - Top Contributor",IF(G14<=0.95,"B - Moderate","C - Low")) -> A - Top Contributor
A15: =Cleaned_Products!A12 -> P1011 | B15: =Cleaned_Products!B12 -> Gold Bracelet #11 | C15: =Cleaned_Products!C12 -> Bracelets | D15: =SUMIF(Cleaned_Sales!$F$2:$F$714,A15,Cleaned_Sales!$K$2:$K$714) -> 2288812 | E15: =SUMIF(Cleaned_Sales!$F$2:$F$714,A15,Cleaned_Sales!$H$2:$H$714) -> 22 | F15: =RANK(D15,$D$5:$D$64) -> 31 | G15: =SUMIF($F$5:$F$64,"<="&F15,$D$5:$D$64)/SUM($D$5:$D$64) -> 0.66630997 | H15: =IF(G15<=0.8,"A - Top Contributor",IF(G15<=0.95,"B - Moderate","C - Low")) -> A - Top Contributor
A16: =Cleaned_Products!A13 -> P1012 | B16: =Cleaned_Products!B13 -> Gold Necklace #12 | C16: =Cleaned_Products!C13 -> Necklaces | D16: =SUMIF(Cleaned_Sales!$F$2:$F$714,A16,Cleaned_Sales!$K$2:$K$714) -> 2542479 | E16: =SUMIF(Cleaned_Sales!$F$2:$F$714,A16,Cleaned_Sales!$H$2:$H$714) -> 19 | F16: =RANK(D16,$D$5:$D$64) -> 22 | G16: =SUMIF($F$5:$F$64,"<="&F16,$D$5:$D$64)/SUM($D$5:$D$64) -> 0.51072872 | H16: =IF(G16<=0.8,"A - Top Contributor",IF(G16<=0.95,"B - Moderate","C - Low")) -> A - Top Contributor
... A64: =Cleaned_Products!A61 -> P1060 | B64: =Cleaned_Products!B61 -> Diamond Pendant #60 | C64: =Cleaned_Products!C61 -> Pendants | D64: =SUMIF(Cleaned_Sales!$F$2:$F$714,A64,Cleaned_Sales!$K$2:$K$714) -> 1178359.5 | E64: =SUMIF(Cleaned_Sales!$F$2:$F$714,A64,Cleaned_Sales!$H$2:$H$714) -> 22 | F64: =RANK(D64,$D$5:$D$64) -> 54 | G64: =SUMIF($F$5:$F$64,"<="&F64,$D$5:$D$64)/SUM($D$5:$D$64) -> 0.9631649 | H64: =IF(G64<=0.8,"A - Top Contributor",IF(G64<=0.95,"B - Moderate","C - Low")) -> C - Low
A67: CUSTOMER SEGMENTATION (Recency / Frequency / Monetary)
A68: CustomerID | B68: CustomerName | C68: TotalSpend | D68: OrderCount | E68: AvgOrderValue | F68: LastPurchaseDate | G68: RecencyDays | H68: Segment | M68: As-of date: | N68: =MAX(Cleaned_Sales!$B$2:$B$714) -> 45876
A69: =Cleaned_Customers!A2 -> C2001 | B69: =Cleaned_Customers!B2 -> Kritika Brar | C69: =SUMIF(Cleaned_Sales!$E$2:$E$714,A69,Cleaned_Sales!$K$2:$K$714) -> 259349 | D69: =COUNTIF(Cleaned_Sales!$E$2:$E$714,A69) -> 2 | E69: =IFERROR(C69/D69,0) -> 129674.5 | F69: =IFERROR(_xlfn.MAXIFS(Cleaned_Sales!$B$2:$B$714,Cleaned_Sales!$E$2:$E$714,A69),"") -> 45603 | G69: =IF(F69="","",$N$68-F69) -> 273 | H69: =IF(D69=0,"No Purchases",IF(AND(C69>=QUARTILE($C$69:$C$217,3),D69>=2),"Champion",IF(C69>=QUARTILE($C$69:$C$217,2),"Loyal",IF(G69>180,"At Risk","Occasional")))) -> At Risk
A70: =Cleaned_Customers!A3 -> C2002 | B70: =Cleaned_Customers!B3 -> Alka Dewan | C70: =SUMIF(Cleaned_Sales!$E$2:$E$714,A70,Cleaned_Sales!$K$2:$K$714) -> 828391 | D70: =COUNTIF(Cleaned_Sales!$E$2:$E$714,A70) -> 4 | E70: =IFERROR(C70/D70,0) -> 207097.75 | F70: =IFERROR(_xlfn.MAXIFS(Cleaned_Sales!$B$2:$B$714,Cleaned_Sales!$E$2:$E$714,A70),"") -> 45707 | G70: =IF(F70="","",$N$68-F70) -> 169 | H70: =IF(D70=0,"No Purchases",IF(AND(C70>=QUARTILE($C$69:$C$217,3),D70>=2),"Champion",IF(C70>=QUARTILE($C$69:$C$217,2),"Loyal",IF(G70>180,"At Risk","Occasional")))) -> Occasional
A71: =Cleaned_Customers!A4 -> C2003 | B71: =Cleaned_Customers!B4 -> Neel Zacharia | C71: =SUMIF(Cleaned_Sales!$E$2:$E$714,A71,Cleaned_Sales!$K$2:$K$714) -> 1081199 | D71: =COUNTIF(Cleaned_Sales!$E$2:$E$714,A71) -> 8 | E71: =IFERROR(C71/D71,0) -> 135149.88 | F71: =IFERROR(_xlfn.MAXIFS(Cleaned_Sales!$B$2:$B$714,Cleaned_Sales!$E$2:$E$714,A71),"") -> 45812 | G71: =IF(F71="","",$N$68-F71) -> 64 | H71: =IF(D71=0,"No Purchases",IF(AND(C71>=QUARTILE($C$69:$C$217,3),D71>=2),"Champion",IF(C71>=QUARTILE($C$69:$C$217,2),"Loyal",IF(G71>180,"At Risk","Occasional")))) -> Loyal
A72: =Cleaned_Customers!A5 -> C2004 | B72: =Cleaned_Customers!B5 -> Veer Bir | C72: =SUMIF(Cleaned_Sales!$E$2:$E$714,A72,Cleaned_Sales!$K$2:$K$714) -> 301700 | D72: =COUNTIF(Cleaned_Sales!$E$2:$E$714,A72) -> 2 | E72: =IFERROR(C72/D72,0) -> 150850 | F72: =IFERROR(_xlfn.MAXIFS(Cleaned_Sales!$B$2:$B$714,Cleaned_Sales!$E$2:$E$714,A72),"") -> 45569 | G72: =IF(F72="","",$N$68-F72) -> 307 | H72: =IF(D72=0,"No Purchases",IF(AND(C72>=QUARTILE($C$69:$C$217,3),D72>=2),"Champion",IF(C72>=QUARTILE($C$69:$C$217,2),"Loyal",IF(G72>180,"At Risk","Occasional")))) -> At Risk
A73: =Cleaned_Customers!A6 -> C2005 | B73: =Cleaned_Customers!B6 -> Girik Khalsa | C73: =SUMIF(Cleaned_Sales!$E$2:$E$714,A73,Cleaned_Sales!$K$2:$K$714) -> 511391 | D73: =COUNTIF(Cleaned_Sales!$E$2:$E$714,A73) -> 3 | E73: =IFERROR(C73/D73,0) -> 170463.67 | F73: =IFERROR(_xlfn.MAXIFS(Cleaned_Sales!$B$2:$B$714,Cleaned_Sales!$E$2:$E$714,A73),"") -> 45867 | G73: =IF(F73="","",$N$68-F73) -> 9 | H73: =IF(D73=0,"No Purchases",IF(AND(C73>=QUARTILE($C$69:$C$217,3),D73>=2),"Champion",IF(C73>=QUARTILE($C$69:$C$217,2),"Loyal",IF(G73>180,"At Risk","Occasional")))) -> Occasional
A74: =Cleaned_Customers!A7 -> C2006 | B74: =Cleaned_Customers!B7 -> Finn Saini | C74: =SUMIF(Cleaned_Sales!$E$2:$E$714,A74,Cleaned_Sales!$K$2:$K$714) -> 161766 | D74: =COUNTIF(Cleaned_Sales!$E$2:$E$714,A74) -> 3 | E74: =IFERROR(C74/D74,0) -> 53922 | F74: =IFERROR(_xlfn.MAXIFS(Cleaned_Sales!$B$2:$B$714,Cleaned_Sales!$E$2:$E$714,A74),"") -> 45381 | G74: =IF(F74="","",$N$68-F74) -> 495 | H74: =IF(D74=0,"No Purchases",IF(AND(C74>=QUARTILE($C$69:$C$217,3),D74>=2),"Champion",IF(C74>=QUARTILE($C$69:$C$217,2),"Loyal",IF(G74>180,"At Risk","Occasional")))) -> At Risk
A75: =Cleaned_Customers!A8 -> C2007 | B75: =Cleaned_Customers!B8 -> Samar Lalla | C75: =SUMIF(Cleaned_Sales!$E$2:$E$714,A75,Cleaned_Sales!$K$2:$K$714) -> 1651725 | D75: =COUNTIF(Cleaned_Sales!$E$2:$E$714,A75) -> 5 | E75: =IFERROR(C75/D75,0) -> 330345 | F75: =IFERROR(_xlfn.MAXIFS(Cleaned_Sales!$B$2:$B$714,Cleaned_Sales!$E$2:$E$714,A75),"") -> 45669 | G75: =IF(F75="","",$N$68-F75) -> 207 | H75: =IF(D75=0,"No Purchases",IF(AND(C75>=QUARTILE($C$69:$C$217,3),D75>=2),"Champion",IF(C75>=QUARTILE($C$69:$C$217,2),"Loyal",IF(G75>180,"At Risk","Occasional")))) -> Champion
A76: =Cleaned_Customers!A9 -> C2008 | B76: =Cleaned_Customers!B9 -> Gaurangi Sabharwal | C76: =SUMIF(Cleaned_Sales!$E$2:$E$714,A76,Cleaned_Sales!$K$2:$K$714) -> 1391243 | D76: =COUNTIF(Cleaned_Sales!$E$2:$E$714,A76) -> 7 | E76: =IFERROR(C76/D76,0) -> 198749 | F76: =IFERROR(_xlfn.MAXIFS(Cleaned_Sales!$B$2:$B$714,Cleaned_Sales!$E$2:$E$714,A76),"") -> 45796 | G76: =IF(F76="","",$N$68-F76) -> 80 | H76: =IF(D76=0,"No Purchases",IF(AND(C76>=QUARTILE($C$69:$C$217,3),D76>=2),"Champion",IF(C76>=QUARTILE($C$69:$C$217,2),"Loyal",IF(G76>180,"At Risk","Occasional")))) -> Champion
A77: =Cleaned_Customers!A10 -> C2009 | B77: =Cleaned_Customers!B10 -> Chaitanya Sarin | C77: =SUMIF(Cleaned_Sales!$E$2:$E$714,A77,Cleaned_Sales!$K$2:$K$714) -> 1018677.5 | D77: =COUNTIF(Cleaned_Sales!$E$2:$E$714,A77) -> 7 | E77: =IFERROR(C77/D77,0) -> 145525.36 | F77: =IFERROR(_xlfn.MAXIFS(Cleaned_Sales!$B$2:$B$714,Cleaned_Sales!$E$2:$E$714,A77),"") -> 45493 | G77: =IF(F77="","",$N$68-F77) -> 383 | H77: =IF(D77=0,"No Purchases",IF(AND(C77>=QUARTILE($C$69:$C$217,3),D77>=2),"Champion",IF(C77>=QUARTILE($C$69:$C$217,2),"Loyal",IF(G77>180,"At Risk","Occasional")))) -> Loyal
A78: =Cleaned_Customers!A11 -> C2010 | B78: =Cleaned_Customers!B11 -> Girik Keer | C78: =SUMIF(Cleaned_Sales!$E$2:$E$714,A78,Cleaned_Sales!$K$2:$K$714) -> 692020 | D78: =COUNTIF(Cleaned_Sales!$E$2:$E$714,A78) -> 3 | E78: =IFERROR(C78/D78,0) -> 230673.33 | F78: =IFERROR(_xlfn.MAXIFS(Cleaned_Sales!$B$2:$B$714,Cleaned_Sales!$E$2:$E$714,A78),"") -> 45511 | G78: =IF(F78="","",$N$68-F78) -> 365 | H78: =IF(D78=0,"No Purchases",IF(AND(C78>=QUARTILE($C$69:$C$217,3),D78>=2),"Champion",IF(C78>=QUARTILE($C$69:$C$217,2),"Loyal",IF(G78>180,"At Risk","Occasional")))) -> At Risk
A79: =Cleaned_Customers!A12 -> C2011 | B79: =Cleaned_Customers!B12 -> William Maharaj | C79: =SUMIF(Cleaned_Sales!$E$2:$E$714,A79,Cleaned_Sales!$K$2:$K$714) -> 1279423.5 | D79: =COUNTIF(Cleaned_Sales!$E$2:$E$714,A79) -> 8 | E79: =IFERROR(C79/D79,0) -> 159927.94 | F79: =IFERROR(_xlfn.MAXIFS(Cleaned_Sales!$B$2:$B$714,Cleaned_Sales!$E$2:$E$714,A79),"") -> 45840 | G79: =IF(F79="","",$N$68-F79) -> 36 | H79: =IF(D79=0,"No Purchases",IF(AND(C79>=QUARTILE($C$69:$C$217,3),D79>=2),"Champion",IF(C79>=QUARTILE($C$69:$C$217,2),"Loyal",IF(G79>180,"At Risk","Occasional")))) -> Champion
A80: =Cleaned_Customers!A13 -> C2012 | B80: =Cleaned_Customers!B13 -> Lopa Nayar | C80: =SUMIF(Cleaned_Sales!$E$2:$E$714,A80,Cleaned_Sales!$K$2:$K$714) -> 596178 | D80: =COUNTIF(Cleaned_Sales!$E$2:$E$714,A80) -> 3 | E80: =IFERROR(C80/D80,0) -> 198726 | F80: =IFERROR(_xlfn.MAXIFS(Cleaned_Sales!$B$2:$B$714,Cleaned_Sales!$E$2:$E$714,A80),"") -> 45868 | G80: =IF(F80="","",$N$68-F80) -> 8 | H80: =IF(D80=0,"No Purchases",IF(AND(C80>=QUARTILE($C$69:$C$217,3),D80>=2),"Champion",IF(C80>=QUARTILE($C$69:$C$217,2),"Loyal",IF(G80>180,"At Risk","Occasional")))) -> Occasional
... A217: =Cleaned_Customers!A150 -> C2150 | B217: =Cleaned_Customers!B150 -> Qasim Sarraf | C217: =SUMIF(Cleaned_Sales!$E$2:$E$714,A217,Cleaned_Sales!$K$2:$K$714) -> 1118691 | D217: =COUNTIF(Cleaned_Sales!$E$2:$E$714,A217) -> 5 | E217: =IFERROR(C217/D217,0) -> 223738.2 | F217: =IFERROR(_xlfn.MAXIFS(Cleaned_Sales!$B$2:$B$714,Cleaned_Sales!$E$2:$E$714,A217),"") -> 45645 | G217: =IF(F217="","",$N$68-F217) -> 231 | H217: =IF(D217=0,"No Purchases",IF(AND(C217>=QUARTILE($C$69:$C$217,3),D217>=2),"Champion",IF(C217>=QUARTILE($C$69:$C$217,2),"Loyal",IF(G217>180,"At Risk","Occasional")))) -> Loyal

Sheet Pivot_Tables
A1: Pivot Summaries (SUMIFS/COUNTIFS-driven — recalculates automatically)
A3: PIVOT 1 — Revenue & Orders by Category
A4: Category | B4: TotalRevenue | C4: TotalQty | D4: OrderCount
A5: Anklets | B5: =SUMIF(Cleaned_Sales!$O$2:$O$714,A5,Cleaned_Sales!$K$2:$K$714) -> 11985194 | C5: =SUMIF(Cleaned_Sales!$O$2:$O$714,A5,Cleaned_Sales!$H$2:$H$714) -> 100 | D5: =COUNTIF(Cleaned_Sales!$O$2:$O$714,A5) -> 62
A6: Bangles | B6: =SUMIF(Cleaned_Sales!$O$2:$O$714,A6,Cleaned_Sales!$K$2:$K$714) -> 19802400 | C6: =SUMIF(Cleaned_Sales!$O$2:$O$714,A6,Cleaned_Sales!$H$2:$H$714) -> 165 | D6: =COUNTIF(Cleaned_Sales!$O$2:$O$714,A6) -> 95
A7: Bracelets | B7: =SUMIF(Cleaned_Sales!$O$2:$O$714,A7,Cleaned_Sales!$K$2:$K$714) -> 27736857 | C7: =SUMIF(Cleaned_Sales!$O$2:$O$714,A7,Cleaned_Sales!$H$2:$H$714) -> 231 | D7: =COUNTIF(Cleaned_Sales!$O$2:$O$714,A7) -> 150
A8: Earrings | B8: =SUMIF(Cleaned_Sales!$O$2:$O$714,A8,Cleaned_Sales!$K$2:$K$714) -> 18156698 | C8: =SUMIF(Cleaned_Sales!$O$2:$O$714,A8,Cleaned_Sales!$H$2:$H$714) -> 153 | D8: =COUNTIF(Cleaned_Sales!$O$2:$O$714,A8) -> 97
A9: Necklaces | B9: =SUMIF(Cleaned_Sales!$O$2:$O$714,A9,Cleaned_Sales!$K$2:$K$714) -> 12047669 | C9: =SUMIF(Cleaned_Sales!$O$2:$O$714,A9,Cleaned_Sales!$H$2:$H$714) -> 98 | D9: =COUNTIF(Cleaned_Sales!$O$2:$O$714,A9) -> 65
A10: Nose Pins | B10: =SUMIF(Cleaned_Sales!$O$2:$O$714,A10,Cleaned_Sales!$K$2:$K$714) -> 21022868 | C10: =SUMIF(Cleaned_Sales!$O$2:$O$714,A10,Cleaned_Sales!$H$2:$H$714) -> 186 | D10: =COUNTIF(Cleaned_Sales!$O$2:$O$714,A10) -> 107
A11: Pendants | B11: =SUMIF(Cleaned_Sales!$O$2:$O$714,A11,Cleaned_Sales!$K$2:$K$714) -> 11928398 | C11: =SUMIF(Cleaned_Sales!$O$2:$O$714,A11,Cleaned_Sales!$H$2:$H$714) -> 113 | D11: =COUNTIF(Cleaned_Sales!$O$2:$O$714,A11) -> 64
A12: Rings | B12: =SUMIF(Cleaned_Sales!$O$2:$O$714,A12,Cleaned_Sales!$K$2:$K$714) -> 17113887 | C12: =SUMIF(Cleaned_Sales!$O$2:$O$714,A12,Cleaned_Sales!$H$2:$H$714) -> 124 | D12: =COUNTIF(Cleaned_Sales!$O$2:$O$714,A12) -> 73
A15: PIVOT 2 — Monthly Revenue Trend
A16: Month | B16: Revenue | C16: OrderCount
A17: 2023-01 | B17: =SUMIF(Cleaned_Sales!$C$2:$C$714,A17,Cleaned_Sales!$K$2:$K$714) -> 6202075.5 | C17: =COUNTIF(Cleaned_Sales!$C$2:$C$714,A17) -> 29
A18: 2023-02 | B18: =SUMIF(Cleaned_Sales!$C$2:$C$714,A18,Cleaned_Sales!$K$2:$K$714) -> 3885979 | C18: =COUNTIF(Cleaned_Sales!$C$2:$C$714,A18) -> 23
A19: 2023-03 | B19: =SUMIF(Cleaned_Sales!$C$2:$C$714,A19,Cleaned_Sales!$K$2:$K$714) -> 4903065 | C19: =COUNTIF(Cleaned_Sales!$C$2:$C$714,A19) -> 24
A20: 2023-04 | B20: =SUMIF(Cleaned_Sales!$C$2:$C$714,A20,Cleaned_Sales!$K$2:$K$714) -> 4104846 | C20: =COUNTIF(Cleaned_Sales!$C$2:$C$714,A20) -> 23
A21: 2023-05 | B21: =SUMIF(Cleaned_Sales!$C$2:$C$714,A21,Cleaned_Sales!$K$2:$K$714) -> 4816490 | C21: =COUNTIF(Cleaned_Sales!$C$2:$C$714,A21) -> 24
A22: 2023-06 | B22: =SUMIF(Cleaned_Sales!$C$2:$C$714,A22,Cleaned_Sales!$K$2:$K$714) -> 3825194.5 | C22: =COUNTIF(Cleaned_Sales!$C$2:$C$714,A22) -> 19
A23: 2023-07 | B23: =SUMIF(Cleaned_Sales!$C$2:$C$714,A23,Cleaned_Sales!$K$2:$K$714) -> 4794524.5 | C23: =COUNTIF(Cleaned_Sales!$C$2:$C$714,A23) -> 25
A24: 2023-08 | B24: =SUMIF(Cleaned_Sales!$C$2:$C$714,A24,Cleaned_Sales!$K$2:$K$714) -> 6262531.5 | C24: =COUNTIF(Cleaned_Sales!$C$2:$C$714,A24) -> 29
A25: 2023-09 | B25: =SUMIF(Cleaned_Sales!$C$2:$C$714,A25,Cleaned_Sales!$K$2:$K$714) -> 4612252 | C25: =COUNTIF(Cleaned_Sales!$C$2:$C$714,A25) -> 23
A26: 2023-10 | B26: =SUMIF(Cleaned_Sales!$C$2:$C$714,A26,Cleaned_Sales!$K$2:$K$714) -> 5052189.5 | C26: =COUNTIF(Cleaned_Sales!$C$2:$C$714,A26) -> 24
A27: 2023-11 | B27: =SUMIF(Cleaned_Sales!$C$2:$C$714,A27,Cleaned_Sales!$K$2:$K$714) -> 3455374.5 | C27: =COUNTIF(Cleaned_Sales!$C$2:$C$714,A27) -> 23
A28: 2023-12 | B28: =SUMIF(Cleaned_Sales!$C$2:$C$714,A28,Cleaned_Sales!$K$2:$K$714) -> 4875028.5 | C28: =COUNTIF(Cleaned_Sales!$C$2:$C$714,A28) -> 25
... A48: 2025-08 | B48: =SUMIF(Cleaned_Sales!$C$2:$C$714,A48,Cleaned_Sales!$K$2:$K$714) -> 225258 | C48: =COUNTIF(Cleaned_Sales!$C$2:$C$714,A48) -> 2
A51: PIVOT 3 — Store-wise Performance
A52: StoreID | B52: StoreName | C52: Revenue | D52: OrderCount
A53: =Cleaned_Stores!A2 -> S101 | B53: =Cleaned_Stores!B2 -> Aurelia Jewels - Surat | C53: =SUMIF(Cleaned_Sales!$G$2:$G$714,A53,Cleaned_Sales!$K$2:$K$714) -> 18442228 | D53: =COUNTIF(Cleaned_Sales!$G$2:$G$714,A53) -> 92
A54: =Cleaned_Stores!A3 -> S102 | B54: =Cleaned_Stores!B3 -> Aurelia Jewels - Chennai | C54: =SUMIF(Cleaned_Sales!$G$2:$G$714,A54,Cleaned_Sales!$K$2:$K$714) -> 20766928 | D54: =COUNTIF(Cleaned_Sales!$G$2:$G$714,A54) -> 94
A55: =Cleaned_Stores!A4 -> S103 | B55: =Cleaned_Stores!B4 -> Aurelia Jewels - Jaipur | C55: =SUMIF(Cleaned_Sales!$G$2:$G$714,A55,Cleaned_Sales!$K$2:$K$714) -> 19313722 | D55: =COUNTIF(Cleaned_Sales!$G$2:$G$714,A55) -> 98
A56: =Cleaned_Stores!A5 -> S104 | B56: =Cleaned_Stores!B5 -> Aurelia Jewels - Ahmedabad | C56: =SUMIF(Cleaned_Sales!$G$2:$G$714,A56,Cleaned_Sales!$K$2:$K$714) -> 16835560 | D56: =COUNTIF(Cleaned_Sales!$G$2:$G$714,A56) -> 92
A57: =Cleaned_Stores!A6 -> S105 | B57: =Cleaned_Stores!B6 -> Aurelia Jewels - Mumbai | C57: =SUMIF(Cleaned_Sales!$G$2:$G$714,A57,Cleaned_Sales!$K$2:$K$714) -> 14641878 | D57: =COUNTIF(Cleaned_Sales!$G$2:$G$714,A57) -> 79
A58: =Cleaned_Stores!A7 -> S106 | B58: =Cleaned_Stores!B7 -> Aurelia Jewels - Lucknow | C58: =SUMIF(Cleaned_Sales!$G$2:$G$714,A58,Cleaned_Sales!$K$2:$K$714) -> 14317814 | D58: =COUNTIF(Cleaned_Sales!$G$2:$G$714,A58) -> 82
A59: =Cleaned_Stores!A8 -> S107 | B59: =Cleaned_Stores!B8 -> Aurelia Jewels - Hyderabad | C59: =SUMIF(Cleaned_Sales!$G$2:$G$714,A59,Cleaned_Sales!$K$2:$K$714) -> 17909226 | D59: =COUNTIF(Cleaned_Sales!$G$2:$G$714,A59) -> 89
A60: =Cleaned_Stores!A9 -> S108 | B60: =Cleaned_Stores!B9 -> Aurelia Jewels - Bengaluru | C60: =SUMIF(Cleaned_Sales!$G$2:$G$714,A60,Cleaned_Sales!$K$2:$K$714) -> 17566616 | D60: =COUNTIF(Cleaned_Sales!$G$2:$G$714,A60) -> 87
A63: PIVOT 4 — Payment Mode Distribution
A64: PaymentMode | B64: Revenue | C64: % of Total Revenue
A65: Cash | B65: =SUMIF(Cleaned_Sales!$L$2:$L$714,A65,Cleaned_Sales!$K$2:$K$714) -> 21566532 | C65: =B65/SUM(Cleaned_Sales!$K$2:$K$714) -> 0.1542737
A66: Credit Card | B66: =SUMIF(Cleaned_Sales!$L$2:$L$714,A66,Cleaned_Sales!$K$2:$K$714) -> 22044695 | C66: =B66/SUM(Cleaned_Sales!$K$2:$K$714) -> 0.15769418
A67: Debit Card | B67: =SUMIF(Cleaned_Sales!$L$2:$L$714,A67,Cleaned_Sales!$K$2:$K$714) -> 21526164 | C67: =B67/SUM(Cleaned_Sales!$K$2:$K$714) -> 0.15398493
A68: EMI | B68: =SUMIF(Cleaned_Sales!$L$2:$L$714,A68,Cleaned_Sales!$K$2:$K$714) -> 25474287 | C68: =B68/SUM(Cleaned_Sales!$K$2:$K$714) -> 0.18222737
A69: Net Banking | B69: =SUMIF(Cleaned_Sales!$L$2:$L$714,A69,Cleaned_Sales!$K$2:$K$714) -> 23107580 | C69: =B69/SUM(Cleaned_Sales!$K$2:$K$714) -> 0.1652974
A70: UPI | B70: =SUMIF(Cleaned_Sales!$L$2:$L$714,A70,Cleaned_Sales!$K$2:$K$714) -> 26074712 | C70: =B70/SUM(Cleaned_Sales!$K$2:$K$714) -> 0.18652244
A73: PIVOT 5 — Top 10 Customers by Revenue
A74: Rank | B74: CustomerName | C74: TotalSpend
A75: 1 | B75: =INDEX(Classification!$B$69:$B$217,MATCH(LARGE(Classification!$C$69:$C$217,1),Classification!$C$69:$C$217,0)) -> Vedhika Sabharwal | C75: =LARGE(Classification!$C$69:$C$217,1) -> 2522996
A76: 2 | B76: =INDEX(Classification!$B$69:$B$217,MATCH(LARGE(Classification!$C$69:$C$217,2),Classification!$C$69:$C$217,0)) -> Max Guha | C76: =LARGE(Classification!$C$69:$C$217,2) -> 2116195.5
A77: 3 | B77: =INDEX(Classification!$B$69:$B$217,MATCH(LARGE(Classification!$C$69:$C$217,3),Classification!$C$69:$C$217,0)) -> Oscar Hans | C77: =LARGE(Classification!$C$69:$C$217,3) -> 2063807
A78: 4 | B78: =INDEX(Classification!$B$69:$B$217,MATCH(LARGE(Classification!$C$69:$C$217,4),Classification!$C$69:$C$217,0)) -> George Wason | C78: =LARGE(Classification!$C$69:$C$217,4) -> 2040661.5
A79: 5 | B79: =INDEX(Classification!$B$69:$B$217,MATCH(LARGE(Classification!$C$69:$C$217,5),Classification!$C$69:$C$217,0)) -> Oliver Kakar | C79: =LARGE(Classification!$C$69:$C$217,5) -> 2010960
A80: 6 | B80: =INDEX(Classification!$B$69:$B$217,MATCH(LARGE(Classification!$C$69:$C$217,6),Classification!$C$69:$C$217,0)) -> Lakshit Dani | C80: =LARGE(Classification!$C$69:$C$217,6) -> 2008606
A81: 7 | B81: =INDEX(Classification!$B$69:$B$217,MATCH(LARGE(Classification!$C$69:$C$217,7),Classification!$C$69:$C$217,0)) -> Elijah Mannan | C81: =LARGE(Classification!$C$69:$C$217,7) -> 1937922
A82: 8 | B82: =INDEX(Classification!$B$69:$B$217,MATCH(LARGE(Classification!$C$69:$C$217,8),Classification!$C$69:$C$217,0)) -> Charles Dugal | C82: =LARGE(Classification!$C$69:$C$217,8) -> 1838089
A83: 9 | B83: =INDEX(Classification!$B$69:$B$217,MATCH(LARGE(Classification!$C$69:$C$217,9),Classification!$C$69:$C$217,0)) -> Widisha Badami | C83: =LARGE(Classification!$C$69:$C$217,9) -> 1796337.5
A84: 10 | B84: =INDEX(Classification!$B$69:$B$217,MATCH(LARGE(Classification!$C$69:$C$217,10),Classification!$C$69:$C$217,0)) -> Victor Kakar | C84: =LARGE(Classification!$C$69:$C$217,10) -> 1737848.5
